[{"nama":"TPS 001","id":33797001,"kode":"3201142003001","tingkat":5,"provinsi":"JAWA BARAT","kode_provinsi":"32","kab_kota":"BOGOR","kode_kab_kota":"3201","kecamatan":"LEUWILIANG","kode_kecamatan":"320114","desa":"KARYASARI","kode_desa":"3201142003"},{"nama":"TPS 002","id":33797002,"kode":"3201142003002","tingkat":5,"provinsi":"JAWA BARAT","kode_provinsi":"32","kab_kota":"BOGOR","kode_kab_kota":"3201","kecamatan":"LEUWILIANG","kode_kecamatan":"320114","desa":"KARYASARI","kode_desa":"3201142003"},{"nama":"TPS 003","id":33797003,"kode":"3201142003003","tingkat":5,"provinsi":"JAWA BARAT","kode_provinsi":"32","kab_kota":"BOGOR","kode_kab_kota":"3201","kecamatan":"LEUWILIANG","kode_kecamatan":"320114","desa":"KARYASARI","kode_desa":"3201142003"},{"nama":"TPS 004","id":33797004,"kode":"3201142003004","tingkat":5,"provinsi":"JAWA BARAT","kode_provinsi":"32","kab_kota":"BOGOR","kode_kab_kota":"3201","kecamatan":"LEUWILIANG","kode_kecamatan":"320114","desa":"KARYASARI","kode_desa":"3201142003"},{"nama":"TPS 005","id":33797005,"kode":"3201142003005","tingkat":5,"provinsi":"JAWA BARAT","kode_provinsi":"32","kab_kota":"BOGOR","kode_kab_kota":"3201","kecamatan":"LEUWILIANG","kode_kecamatan":"320114","desa":"KARYASARI","kode_desa":"3201142003"},{"nama":"TPS 006","id":33797006,"kode":"3201142003006","tingkat":5,"provinsi":"JAWA BARAT","kode_provinsi":"32","kab_kota":"BOGOR","kode_kab_kota":"3201","kecamatan":"LEUWILIANG","kode_kecamatan":"320114","desa":"KARYASARI","kode_desa":"3201142003"},{"nama":"TPS 007","id":33797007,"kode":"3201142003007","tingkat":5,"provinsi":"JAWA BARAT","kode_provinsi":"32","kab_kota":"BOGOR","kode_kab_kota":"3201","kecamatan":"LEUWILIANG","kode_kecamatan":"320114","desa":"KARYASARI","kode_desa":"3201142003"},{"nama":"TPS 008","id":33797008,"kode":"3201142003008","tingkat":5,"provinsi":"JAWA BARAT","kode_provinsi":"32","kab_kota":"BOGOR","kode_kab_kota":"3201","kecamatan":"LEUWILIANG","kode_kecamatan":"320114","desa":"KARYASARI","kode_desa":"3201142003"},{"nama":"TPS 009","id":33797009,"kode":"3201142003009","tingkat":5,"provinsi":"JAWA BARAT","kode_provinsi":"32","kab_kota":"BOGOR","kode_kab_kota":"3201","kecamatan":"LEUWILIANG","kode_kecamatan":"320114","desa":"KARYASARI","kode_desa":"3201142003"},{"nama":"TPS 010","id":33797010,"kode":"3201142003010","tingkat":5,"provinsi":"JAWA BARAT","kode_provinsi":"32","kab_kota":"BOGOR","kode_kab_kota":"3201","kecamatan":"LEUWILIANG","kode_kecamatan":"320114","desa":"KARYASARI","kode_desa":"3201142003"},{"nama":"TPS 011","id":33797011,"kode":"3201142003011","tingkat":5,"provinsi":"JAWA BARAT","kode_provinsi":"32","kab_kota":"BOGOR","kode_kab_kota":"3201","kecamatan":"LEUWILIANG","kode_kecamatan":"320114","desa":"KARYASARI","kode_desa":"3201142003"},{"nama":"TPS 012","id":33797012,"kode":"3201142003012","tingkat":5,"provinsi":"JAWA BARAT","kode_provinsi":"32","kab_kota":"BOGOR","kode_kab_kota":"3201","kecamatan":"LEUWILIANG","kode_kecamatan":"320114","desa":"KARYASARI","kode_desa":"3201142003"},{"nama":"TPS 013","id":33797013,"kode":"3201142003013","tingkat":5,"provinsi":"JAWA BARAT","kode_provinsi":"32","kab_kota":"BOGOR","kode_kab_kota":"3201","kecamatan":"LEUWILIANG","kode_kecamatan":"320114","desa":"KARYASARI","kode_desa":"3201142003"},{"nama":"TPS 014","id":33797014,"kode":"3201142003014","tingkat":5,"provinsi":"JAWA BARAT","kode_provinsi":"32","kab_kota":"BOGOR","kode_kab_kota":"3201","kecamatan":"LEUWILIANG","kode_kecamatan":"320114","desa":"KARYASARI","kode_desa":"3201142003"},{"nama":"TPS 015","id":33797015,"kode":"3201142003015","tingkat":5,"provinsi":"JAWA BARAT","kode_provinsi":"32","kab_kota":"BOGOR","kode_kab_kota":"3201","kecamatan":"LEUWILIANG","kode_kecamatan":"320114","desa":"KARYASARI","kode_desa":"3201142003"},{"nama":"TPS 016","id":33797016,"kode":"3201142003016","tingkat":5,"provinsi":"JAWA BARAT","kode_provinsi":"32","kab_kota":"BOGOR","kode_kab_kota":"3201","kecamatan":"LEUWILIANG","kode_kecamatan":"320114","desa":"KARYASARI","kode_desa":"3201142003"},{"nama":"TPS 017","id":33797017,"kode":"3201142003017","tingkat":5,"provinsi":"JAWA BARAT","kode_provinsi":"32","kab_kota":"BOGOR","kode_kab_kota":"3201","kecamatan":"LEUWILIANG","kode_kecamatan":"320114","desa":"KARYASARI","kode_desa":"3201142003"},{"nama":"TPS 018","id":33797018,"kode":"3201142003018","tingkat":5,"provinsi":"JAWA BARAT","kode_provinsi":"32","kab_kota":"BOGOR","kode_kab_kota":"3201","kecamatan":"LEUWILIANG","kode_kecamatan":"320114","desa":"KARYASARI","kode_desa":"3201142003"},{"nama":"TPS 019","id":33797019,"kode":"3201142003019","tingkat":5,"provinsi":"JAWA BARAT","kode_provinsi":"32","kab_kota":"BOGOR","kode_kab_kota":"3201","kecamatan":"LEUWILIANG","kode_kecamatan":"320114","desa":"KARYASARI","kode_desa":"3201142003"},{"nama":"TPS 020","id":33797020,"kode":"3201142003020","tingkat":5,"provinsi":"JAWA BARAT","kode_provinsi":"32","kab_kota":"BOGOR","kode_kab_kota":"3201","kecamatan":"LEUWILIANG","kode_kecamatan":"320114","desa":"KARYASARI","kode_desa":"3201142003"},{"nama":"TPS 021","id":33797021,"kode":"3201142003021","tingkat":5,"provinsi":"JAWA BARAT","kode_provinsi":"32","kab_kota":"BOGOR","kode_kab_kota":"3201","kecamatan":"LEUWILIANG","kode_kecamatan":"320114","desa":"KARYASARI","kode_desa":"3201142003"},{"nama":"TPS 022","id":33797022,"kode":"3201142003022","tingkat":5,"provinsi":"JAWA BARAT","kode_provinsi":"32","kab_kota":"BOGOR","kode_kab_kota":"3201","kecamatan":"LEUWILIANG","kode_kecamatan":"320114","desa":"KARYASARI","kode_desa":"3201142003"},{"nama":"TPS 023","id":33797023,"kode":"3201142003023","tingkat":5,"provinsi":"JAWA BARAT","kode_provinsi":"32","kab_kota":"BOGOR","kode_kab_kota":"3201","kecamatan":"LEUWILIANG","kode_kecamatan":"320114","desa":"KARYASARI","kode_desa":"3201142003"},{"nama":"TPS 024","id":33797024,"kode":"3201142003024","tingkat":5,"provinsi":"JAWA BARAT","kode_provinsi":"32","kab_kota":"BOGOR","kode_kab_kota":"3201","kecamatan":"LEUWILIANG","kode_kecamatan":"320114","desa":"KARYASARI","kode_desa":"3201142003"},{"nama":"TPS 025","id":33797025,"kode":"3201142003025","tingkat":5,"provinsi":"JAWA BARAT","kode_provinsi":"32","kab_kota":"BOGOR","kode_kab_kota":"3201","kecamatan":"LEUWILIANG","kode_kecamatan":"320114","desa":"KARYASARI","kode_desa":"3201142003"},{"nama":"TPS 026","id":33797026,"kode":"3201142003026","tingkat":5,"provinsi":"JAWA BARAT","kode_provinsi":"32","kab_kota":"BOGOR","kode_kab_kota":"3201","kecamatan":"LEUWILIANG","kode_kecamatan":"320114","desa":"KARYASARI","kode_desa":"3201142003"},{"nama":"TPS 027","id":33797027,"kode":"3201142003027","tingkat":5,"provinsi":"JAWA BARAT","kode_provinsi":"32","kab_kota":"BOGOR","kode_kab_kota":"3201","kecamatan":"LEUWILIANG","kode_kecamatan":"320114","desa":"KARYASARI","kode_desa":"3201142003"},{"nama":"TPS 028","id":33797028,"kode":"3201142003028","tingkat":5,"provinsi":"JAWA BARAT","kode_provinsi":"32","kab_kota":"BOGOR","kode_kab_kota":"3201","kecamatan":"LEUWILIANG","kode_kecamatan":"320114","desa":"KARYASARI","kode_desa":"3201142003"},{"nama":"TPS 029","id":33797029,"kode":"3201142003029","tingkat":5,"provinsi":"JAWA BARAT","kode_provinsi":"32","kab_kota":"BOGOR","kode_kab_kota":"3201","kecamatan":"LEUWILIANG","kode_kecamatan":"320114","desa":"KARYASARI","kode_desa":"3201142003"},{"nama":"TPS 030","id":33797030,"kode":"3201142003030","tingkat":5,"provinsi":"JAWA BARAT","kode_provinsi":"32","kab_kota":"BOGOR","kode_kab_kota":"3201","kecamatan":"LEUWILIANG","kode_kecamatan":"320114","desa":"KARYASARI","kode_desa":"3201142003"},{"nama":"TPS 031","id":33797031,"kode":"3201142003031","tingkat":5,"provinsi":"JAWA BARAT","kode_provinsi":"32","kab_kota":"BOGOR","kode_kab_kota":"3201","kecamatan":"LEUWILIANG","kode_kecamatan":"320114","desa":"KARYASARI","kode_desa":"3201142003"}]