[{"nama":"TPS 001","id":34173001,"kode":"3202092012001","tingkat":5,"provinsi":"JAWA BARAT","kode_provinsi":"32","kab_kota":"SUKABUMI","kode_kab_kota":"3202","kecamatan":"WARUNGKIARA","kode_kecamatan":"320209","desa":"TARISI","kode_desa":"3202092012"},{"nama":"TPS 002","id":34173002,"kode":"3202092012002","tingkat":5,"provinsi":"JAWA BARAT","kode_provinsi":"32","kab_kota":"SUKABUMI","kode_kab_kota":"3202","kecamatan":"WARUNGKIARA","kode_kecamatan":"320209","desa":"TARISI","kode_desa":"3202092012"},{"nama":"TPS 003","id":34173003,"kode":"3202092012003","tingkat":5,"provinsi":"JAWA BARAT","kode_provinsi":"32","kab_kota":"SUKABUMI","kode_kab_kota":"3202","kecamatan":"WARUNGKIARA","kode_kecamatan":"320209","desa":"TARISI","kode_desa":"3202092012"},{"nama":"TPS 004","id":34173004,"kode":"3202092012004","tingkat":5,"provinsi":"JAWA BARAT","kode_provinsi":"32","kab_kota":"SUKABUMI","kode_kab_kota":"3202","kecamatan":"WARUNGKIARA","kode_kecamatan":"320209","desa":"TARISI","kode_desa":"3202092012"},{"nama":"TPS 005","id":34173005,"kode":"3202092012005","tingkat":5,"provinsi":"JAWA BARAT","kode_provinsi":"32","kab_kota":"SUKABUMI","kode_kab_kota":"3202","kecamatan":"WARUNGKIARA","kode_kecamatan":"320209","desa":"TARISI","kode_desa":"3202092012"},{"nama":"TPS 006","id":34173006,"kode":"3202092012006","tingkat":5,"provinsi":"JAWA BARAT","kode_provinsi":"32","kab_kota":"SUKABUMI","kode_kab_kota":"3202","kecamatan":"WARUNGKIARA","kode_kecamatan":"320209","desa":"TARISI","kode_desa":"3202092012"},{"nama":"TPS 007","id":34173007,"kode":"3202092012007","tingkat":5,"provinsi":"JAWA BARAT","kode_provinsi":"32","kab_kota":"SUKABUMI","kode_kab_kota":"3202","kecamatan":"WARUNGKIARA","kode_kecamatan":"320209","desa":"TARISI","kode_desa":"3202092012"}]