[{"nama":"TPS 001","id":34562001,"kode":"3203082003001","tingkat":5,"provinsi":"JAWA BARAT","kode_provinsi":"32","kab_kota":"CIANJUR","kode_kab_kota":"3203","kecamatan":"MANDE","kode_kecamatan":"320308","desa":"JAMALI","kode_desa":"3203082003"},{"nama":"TPS 002","id":34562002,"kode":"3203082003002","tingkat":5,"provinsi":"JAWA BARAT","kode_provinsi":"32","kab_kota":"CIANJUR","kode_kab_kota":"3203","kecamatan":"MANDE","kode_kecamatan":"320308","desa":"JAMALI","kode_desa":"3203082003"},{"nama":"TPS 003","id":34562003,"kode":"3203082003003","tingkat":5,"provinsi":"JAWA BARAT","kode_provinsi":"32","kab_kota":"CIANJUR","kode_kab_kota":"3203","kecamatan":"MANDE","kode_kecamatan":"320308","desa":"JAMALI","kode_desa":"3203082003"},{"nama":"TPS 004","id":34562004,"kode":"3203082003004","tingkat":5,"provinsi":"JAWA BARAT","kode_provinsi":"32","kab_kota":"CIANJUR","kode_kab_kota":"3203","kecamatan":"MANDE","kode_kecamatan":"320308","desa":"JAMALI","kode_desa":"3203082003"},{"nama":"TPS 005","id":34562005,"kode":"3203082003005","tingkat":5,"provinsi":"JAWA BARAT","kode_provinsi":"32","kab_kota":"CIANJUR","kode_kab_kota":"3203","kecamatan":"MANDE","kode_kecamatan":"320308","desa":"JAMALI","kode_desa":"3203082003"},{"nama":"TPS 006","id":34562006,"kode":"3203082003006","tingkat":5,"provinsi":"JAWA BARAT","kode_provinsi":"32","kab_kota":"CIANJUR","kode_kab_kota":"3203","kecamatan":"MANDE","kode_kecamatan":"320308","desa":"JAMALI","kode_desa":"3203082003"},{"nama":"TPS 007","id":34562007,"kode":"3203082003007","tingkat":5,"provinsi":"JAWA BARAT","kode_provinsi":"32","kab_kota":"CIANJUR","kode_kab_kota":"3203","kecamatan":"MANDE","kode_kecamatan":"320308","desa":"JAMALI","kode_desa":"3203082003"},{"nama":"TPS 008","id":34562008,"kode":"3203082003008","tingkat":5,"provinsi":"JAWA BARAT","kode_provinsi":"32","kab_kota":"CIANJUR","kode_kab_kota":"3203","kecamatan":"MANDE","kode_kecamatan":"320308","desa":"JAMALI","kode_desa":"3203082003"},{"nama":"TPS 009","id":34562009,"kode":"3203082003009","tingkat":5,"provinsi":"JAWA BARAT","kode_provinsi":"32","kab_kota":"CIANJUR","kode_kab_kota":"3203","kecamatan":"MANDE","kode_kecamatan":"320308","desa":"JAMALI","kode_desa":"3203082003"},{"nama":"TPS 010","id":34562010,"kode":"3203082003010","tingkat":5,"provinsi":"JAWA BARAT","kode_provinsi":"32","kab_kota":"CIANJUR","kode_kab_kota":"3203","kecamatan":"MANDE","kode_kecamatan":"320308","desa":"JAMALI","kode_desa":"3203082003"},{"nama":"TPS 011","id":34562011,"kode":"3203082003011","tingkat":5,"provinsi":"JAWA BARAT","kode_provinsi":"32","kab_kota":"CIANJUR","kode_kab_kota":"3203","kecamatan":"MANDE","kode_kecamatan":"320308","desa":"JAMALI","kode_desa":"3203082003"},{"nama":"TPS 012","id":34562012,"kode":"3203082003012","tingkat":5,"provinsi":"JAWA BARAT","kode_provinsi":"32","kab_kota":"CIANJUR","kode_kab_kota":"3203","kecamatan":"MANDE","kode_kecamatan":"320308","desa":"JAMALI","kode_desa":"3203082003"},{"nama":"TPS 013","id":34562013,"kode":"3203082003013","tingkat":5,"provinsi":"JAWA BARAT","kode_provinsi":"32","kab_kota":"CIANJUR","kode_kab_kota":"3203","kecamatan":"MANDE","kode_kecamatan":"320308","desa":"JAMALI","kode_desa":"3203082003"},{"nama":"TPS 014","id":34562014,"kode":"3203082003014","tingkat":5,"provinsi":"JAWA BARAT","kode_provinsi":"32","kab_kota":"CIANJUR","kode_kab_kota":"3203","kecamatan":"MANDE","kode_kecamatan":"320308","desa":"JAMALI","kode_desa":"3203082003"},{"nama":"TPS 015","id":34562015,"kode":"3203082003015","tingkat":5,"provinsi":"JAWA BARAT","kode_provinsi":"32","kab_kota":"CIANJUR","kode_kab_kota":"3203","kecamatan":"MANDE","kode_kecamatan":"320308","desa":"JAMALI","kode_desa":"3203082003"},{"nama":"TPS 016","id":34562016,"kode":"3203082003016","tingkat":5,"provinsi":"JAWA BARAT","kode_provinsi":"32","kab_kota":"CIANJUR","kode_kab_kota":"3203","kecamatan":"MANDE","kode_kecamatan":"320308","desa":"JAMALI","kode_desa":"3203082003"},{"nama":"TPS 017","id":34562017,"kode":"3203082003017","tingkat":5,"provinsi":"JAWA BARAT","kode_provinsi":"32","kab_kota":"CIANJUR","kode_kab_kota":"3203","kecamatan":"MANDE","kode_kecamatan":"320308","desa":"JAMALI","kode_desa":"3203082003"},{"nama":"TPS 018","id":34562018,"kode":"3203082003018","tingkat":5,"provinsi":"JAWA BARAT","kode_provinsi":"32","kab_kota":"CIANJUR","kode_kab_kota":"3203","kecamatan":"MANDE","kode_kecamatan":"320308","desa":"JAMALI","kode_desa":"3203082003"},{"nama":"TPS 019","id":34562019,"kode":"3203082003019","tingkat":5,"provinsi":"JAWA BARAT","kode_provinsi":"32","kab_kota":"CIANJUR","kode_kab_kota":"3203","kecamatan":"MANDE","kode_kecamatan":"320308","desa":"JAMALI","kode_desa":"3203082003"},{"nama":"TPS 020","id":34562020,"kode":"3203082003020","tingkat":5,"provinsi":"JAWA BARAT","kode_provinsi":"32","kab_kota":"CIANJUR","kode_kab_kota":"3203","kecamatan":"MANDE","kode_kecamatan":"320308","desa":"JAMALI","kode_desa":"3203082003"},{"nama":"TPS 021","id":34562021,"kode":"3203082003021","tingkat":5,"provinsi":"JAWA BARAT","kode_provinsi":"32","kab_kota":"CIANJUR","kode_kab_kota":"3203","kecamatan":"MANDE","kode_kecamatan":"320308","desa":"JAMALI","kode_desa":"3203082003"},{"nama":"TPS 022","id":34562022,"kode":"3203082003022","tingkat":5,"provinsi":"JAWA BARAT","kode_provinsi":"32","kab_kota":"CIANJUR","kode_kab_kota":"3203","kecamatan":"MANDE","kode_kecamatan":"320308","desa":"JAMALI","kode_desa":"3203082003"},{"nama":"TPS 023","id":34562023,"kode":"3203082003023","tingkat":5,"provinsi":"JAWA BARAT","kode_provinsi":"32","kab_kota":"CIANJUR","kode_kab_kota":"3203","kecamatan":"MANDE","kode_kecamatan":"320308","desa":"JAMALI","kode_desa":"3203082003"},{"nama":"TPS 024","id":34562024,"kode":"3203082003024","tingkat":5,"provinsi":"JAWA BARAT","kode_provinsi":"32","kab_kota":"CIANJUR","kode_kab_kota":"3203","kecamatan":"MANDE","kode_kecamatan":"320308","desa":"JAMALI","kode_desa":"3203082003"},{"nama":"TPS 025","id":34562025,"kode":"3203082003025","tingkat":5,"provinsi":"JAWA BARAT","kode_provinsi":"32","kab_kota":"CIANJUR","kode_kab_kota":"3203","kecamatan":"MANDE","kode_kecamatan":"320308","desa":"JAMALI","kode_desa":"3203082003"},{"nama":"TPS 026","id":34562026,"kode":"3203082003026","tingkat":5,"provinsi":"JAWA BARAT","kode_provinsi":"32","kab_kota":"CIANJUR","kode_kab_kota":"3203","kecamatan":"MANDE","kode_kecamatan":"320308","desa":"JAMALI","kode_desa":"3203082003"},{"nama":"TPS 027","id":34562027,"kode":"3203082003027","tingkat":5,"provinsi":"JAWA BARAT","kode_provinsi":"32","kab_kota":"CIANJUR","kode_kab_kota":"3203","kecamatan":"MANDE","kode_kecamatan":"320308","desa":"JAMALI","kode_desa":"3203082003"},{"nama":"TPS 028","id":34562028,"kode":"3203082003028","tingkat":5,"provinsi":"JAWA BARAT","kode_provinsi":"32","kab_kota":"CIANJUR","kode_kab_kota":"3203","kecamatan":"MANDE","kode_kecamatan":"320308","desa":"JAMALI","kode_desa":"3203082003"},{"nama":"TPS 029","id":34562029,"kode":"3203082003029","tingkat":5,"provinsi":"JAWA BARAT","kode_provinsi":"32","kab_kota":"CIANJUR","kode_kab_kota":"3203","kecamatan":"MANDE","kode_kecamatan":"320308","desa":"JAMALI","kode_desa":"3203082003"},{"nama":"TPS 030","id":34562030,"kode":"3203082003030","tingkat":5,"provinsi":"JAWA BARAT","kode_provinsi":"32","kab_kota":"CIANJUR","kode_kab_kota":"3203","kecamatan":"MANDE","kode_kecamatan":"320308","desa":"JAMALI","kode_desa":"3203082003"},{"nama":"TPS 031","id":34562031,"kode":"3203082003031","tingkat":5,"provinsi":"JAWA BARAT","kode_provinsi":"32","kab_kota":"CIANJUR","kode_kab_kota":"3203","kecamatan":"MANDE","kode_kecamatan":"320308","desa":"JAMALI","kode_desa":"3203082003"},{"nama":"TPS 032","id":34562032,"kode":"3203082003032","tingkat":5,"provinsi":"JAWA BARAT","kode_provinsi":"32","kab_kota":"CIANJUR","kode_kab_kota":"3203","kecamatan":"MANDE","kode_kecamatan":"320308","desa":"JAMALI","kode_desa":"3203082003"},{"nama":"TPS 033","id":34562033,"kode":"3203082003033","tingkat":5,"provinsi":"JAWA BARAT","kode_provinsi":"32","kab_kota":"CIANJUR","kode_kab_kota":"3203","kecamatan":"MANDE","kode_kecamatan":"320308","desa":"JAMALI","kode_desa":"3203082003"},{"nama":"TPS 034","id":34562034,"kode":"3203082003034","tingkat":5,"provinsi":"JAWA BARAT","kode_provinsi":"32","kab_kota":"CIANJUR","kode_kab_kota":"3203","kecamatan":"MANDE","kode_kecamatan":"320308","desa":"JAMALI","kode_desa":"3203082003"},{"nama":"TPS 035","id":34562035,"kode":"3203082003035","tingkat":5,"provinsi":"JAWA BARAT","kode_provinsi":"32","kab_kota":"CIANJUR","kode_kab_kota":"3203","kecamatan":"MANDE","kode_kecamatan":"320308","desa":"JAMALI","kode_desa":"3203082003"},{"nama":"TPS 036","id":34562036,"kode":"3203082003036","tingkat":5,"provinsi":"JAWA BARAT","kode_provinsi":"32","kab_kota":"CIANJUR","kode_kab_kota":"3203","kecamatan":"MANDE","kode_kecamatan":"320308","desa":"JAMALI","kode_desa":"3203082003"},{"nama":"TPS 037","id":34562037,"kode":"3203082003037","tingkat":5,"provinsi":"JAWA BARAT","kode_provinsi":"32","kab_kota":"CIANJUR","kode_kab_kota":"3203","kecamatan":"MANDE","kode_kecamatan":"320308","desa":"JAMALI","kode_desa":"3203082003"}]