[{"nama":"TPS 001","id":34651001,"kode":"3203152008001","tingkat":5,"provinsi":"JAWA BARAT","kode_provinsi":"32","kab_kota":"CIANJUR","kode_kab_kota":"3203","kecamatan":"CAMPAKA","kode_kecamatan":"320315","desa":"CAMPAKA","kode_desa":"3203152008"},{"nama":"TPS 002","id":34651002,"kode":"3203152008002","tingkat":5,"provinsi":"JAWA BARAT","kode_provinsi":"32","kab_kota":"CIANJUR","kode_kab_kota":"3203","kecamatan":"CAMPAKA","kode_kecamatan":"320315","desa":"CAMPAKA","kode_desa":"3203152008"},{"nama":"TPS 003","id":34651003,"kode":"3203152008003","tingkat":5,"provinsi":"JAWA BARAT","kode_provinsi":"32","kab_kota":"CIANJUR","kode_kab_kota":"3203","kecamatan":"CAMPAKA","kode_kecamatan":"320315","desa":"CAMPAKA","kode_desa":"3203152008"},{"nama":"TPS 004","id":34651004,"kode":"3203152008004","tingkat":5,"provinsi":"JAWA BARAT","kode_provinsi":"32","kab_kota":"CIANJUR","kode_kab_kota":"3203","kecamatan":"CAMPAKA","kode_kecamatan":"320315","desa":"CAMPAKA","kode_desa":"3203152008"},{"nama":"TPS 005","id":34651005,"kode":"3203152008005","tingkat":5,"provinsi":"JAWA BARAT","kode_provinsi":"32","kab_kota":"CIANJUR","kode_kab_kota":"3203","kecamatan":"CAMPAKA","kode_kecamatan":"320315","desa":"CAMPAKA","kode_desa":"3203152008"},{"nama":"TPS 006","id":34651006,"kode":"3203152008006","tingkat":5,"provinsi":"JAWA BARAT","kode_provinsi":"32","kab_kota":"CIANJUR","kode_kab_kota":"3203","kecamatan":"CAMPAKA","kode_kecamatan":"320315","desa":"CAMPAKA","kode_desa":"3203152008"},{"nama":"TPS 007","id":34651007,"kode":"3203152008007","tingkat":5,"provinsi":"JAWA BARAT","kode_provinsi":"32","kab_kota":"CIANJUR","kode_kab_kota":"3203","kecamatan":"CAMPAKA","kode_kecamatan":"320315","desa":"CAMPAKA","kode_desa":"3203152008"},{"nama":"TPS 008","id":34651008,"kode":"3203152008008","tingkat":5,"provinsi":"JAWA BARAT","kode_provinsi":"32","kab_kota":"CIANJUR","kode_kab_kota":"3203","kecamatan":"CAMPAKA","kode_kecamatan":"320315","desa":"CAMPAKA","kode_desa":"3203152008"},{"nama":"TPS 009","id":34651009,"kode":"3203152008009","tingkat":5,"provinsi":"JAWA BARAT","kode_provinsi":"32","kab_kota":"CIANJUR","kode_kab_kota":"3203","kecamatan":"CAMPAKA","kode_kecamatan":"320315","desa":"CAMPAKA","kode_desa":"3203152008"},{"nama":"TPS 010","id":34651010,"kode":"3203152008010","tingkat":5,"provinsi":"JAWA BARAT","kode_provinsi":"32","kab_kota":"CIANJUR","kode_kab_kota":"3203","kecamatan":"CAMPAKA","kode_kecamatan":"320315","desa":"CAMPAKA","kode_desa":"3203152008"},{"nama":"TPS 011","id":34651011,"kode":"3203152008011","tingkat":5,"provinsi":"JAWA BARAT","kode_provinsi":"32","kab_kota":"CIANJUR","kode_kab_kota":"3203","kecamatan":"CAMPAKA","kode_kecamatan":"320315","desa":"CAMPAKA","kode_desa":"3203152008"},{"nama":"TPS 012","id":34651012,"kode":"3203152008012","tingkat":5,"provinsi":"JAWA BARAT","kode_provinsi":"32","kab_kota":"CIANJUR","kode_kab_kota":"3203","kecamatan":"CAMPAKA","kode_kecamatan":"320315","desa":"CAMPAKA","kode_desa":"3203152008"},{"nama":"TPS 013","id":34651013,"kode":"3203152008013","tingkat":5,"provinsi":"JAWA BARAT","kode_provinsi":"32","kab_kota":"CIANJUR","kode_kab_kota":"3203","kecamatan":"CAMPAKA","kode_kecamatan":"320315","desa":"CAMPAKA","kode_desa":"3203152008"},{"nama":"TPS 014","id":34651014,"kode":"3203152008014","tingkat":5,"provinsi":"JAWA BARAT","kode_provinsi":"32","kab_kota":"CIANJUR","kode_kab_kota":"3203","kecamatan":"CAMPAKA","kode_kecamatan":"320315","desa":"CAMPAKA","kode_desa":"3203152008"},{"nama":"TPS 015","id":34651015,"kode":"3203152008015","tingkat":5,"provinsi":"JAWA BARAT","kode_provinsi":"32","kab_kota":"CIANJUR","kode_kab_kota":"3203","kecamatan":"CAMPAKA","kode_kecamatan":"320315","desa":"CAMPAKA","kode_desa":"3203152008"}]