[{"nama":"TPS 001","id":35337001,"kode":"3205192006001","tingkat":5,"provinsi":"JAWA BARAT","kode_provinsi":"32","kab_kota":"GARUT","kode_kab_kota":"3205","kecamatan":"CILAWU","kode_kecamatan":"320519","desa":"SUKAHATI","kode_desa":"3205192006"},{"nama":"TPS 002","id":35337002,"kode":"3205192006002","tingkat":5,"provinsi":"JAWA BARAT","kode_provinsi":"32","kab_kota":"GARUT","kode_kab_kota":"3205","kecamatan":"CILAWU","kode_kecamatan":"320519","desa":"SUKAHATI","kode_desa":"3205192006"},{"nama":"TPS 003","id":35337003,"kode":"3205192006003","tingkat":5,"provinsi":"JAWA BARAT","kode_provinsi":"32","kab_kota":"GARUT","kode_kab_kota":"3205","kecamatan":"CILAWU","kode_kecamatan":"320519","desa":"SUKAHATI","kode_desa":"3205192006"},{"nama":"TPS 004","id":35337004,"kode":"3205192006004","tingkat":5,"provinsi":"JAWA BARAT","kode_provinsi":"32","kab_kota":"GARUT","kode_kab_kota":"3205","kecamatan":"CILAWU","kode_kecamatan":"320519","desa":"SUKAHATI","kode_desa":"3205192006"},{"nama":"TPS 005","id":35337005,"kode":"3205192006005","tingkat":5,"provinsi":"JAWA BARAT","kode_provinsi":"32","kab_kota":"GARUT","kode_kab_kota":"3205","kecamatan":"CILAWU","kode_kecamatan":"320519","desa":"SUKAHATI","kode_desa":"3205192006"},{"nama":"TPS 006","id":35337006,"kode":"3205192006006","tingkat":5,"provinsi":"JAWA BARAT","kode_provinsi":"32","kab_kota":"GARUT","kode_kab_kota":"3205","kecamatan":"CILAWU","kode_kecamatan":"320519","desa":"SUKAHATI","kode_desa":"3205192006"},{"nama":"TPS 007","id":35337007,"kode":"3205192006007","tingkat":5,"provinsi":"JAWA BARAT","kode_provinsi":"32","kab_kota":"GARUT","kode_kab_kota":"3205","kecamatan":"CILAWU","kode_kecamatan":"320519","desa":"SUKAHATI","kode_desa":"3205192006"},{"nama":"TPS 008","id":35337008,"kode":"3205192006008","tingkat":5,"provinsi":"JAWA BARAT","kode_provinsi":"32","kab_kota":"GARUT","kode_kab_kota":"3205","kecamatan":"CILAWU","kode_kecamatan":"320519","desa":"SUKAHATI","kode_desa":"3205192006"},{"nama":"TPS 009","id":35337009,"kode":"3205192006009","tingkat":5,"provinsi":"JAWA BARAT","kode_provinsi":"32","kab_kota":"GARUT","kode_kab_kota":"3205","kecamatan":"CILAWU","kode_kecamatan":"320519","desa":"SUKAHATI","kode_desa":"3205192006"},{"nama":"TPS 010","id":35337010,"kode":"3205192006010","tingkat":5,"provinsi":"JAWA BARAT","kode_provinsi":"32","kab_kota":"GARUT","kode_kab_kota":"3205","kecamatan":"CILAWU","kode_kecamatan":"320519","desa":"SUKAHATI","kode_desa":"3205192006"},{"nama":"TPS 011","id":35337011,"kode":"3205192006011","tingkat":5,"provinsi":"JAWA BARAT","kode_provinsi":"32","kab_kota":"GARUT","kode_kab_kota":"3205","kecamatan":"CILAWU","kode_kecamatan":"320519","desa":"SUKAHATI","kode_desa":"3205192006"},{"nama":"TPS 012","id":35337012,"kode":"3205192006012","tingkat":5,"provinsi":"JAWA BARAT","kode_provinsi":"32","kab_kota":"GARUT","kode_kab_kota":"3205","kecamatan":"CILAWU","kode_kecamatan":"320519","desa":"SUKAHATI","kode_desa":"3205192006"},{"nama":"TPS 013","id":35337013,"kode":"3205192006013","tingkat":5,"provinsi":"JAWA BARAT","kode_provinsi":"32","kab_kota":"GARUT","kode_kab_kota":"3205","kecamatan":"CILAWU","kode_kecamatan":"320519","desa":"SUKAHATI","kode_desa":"3205192006"},{"nama":"TPS 014","id":35337014,"kode":"3205192006014","tingkat":5,"provinsi":"JAWA BARAT","kode_provinsi":"32","kab_kota":"GARUT","kode_kab_kota":"3205","kecamatan":"CILAWU","kode_kecamatan":"320519","desa":"SUKAHATI","kode_desa":"3205192006"},{"nama":"TPS 015","id":35337015,"kode":"3205192006015","tingkat":5,"provinsi":"JAWA BARAT","kode_provinsi":"32","kab_kota":"GARUT","kode_kab_kota":"3205","kecamatan":"CILAWU","kode_kecamatan":"320519","desa":"SUKAHATI","kode_desa":"3205192006"},{"nama":"TPS 016","id":35337016,"kode":"3205192006016","tingkat":5,"provinsi":"JAWA BARAT","kode_provinsi":"32","kab_kota":"GARUT","kode_kab_kota":"3205","kecamatan":"CILAWU","kode_kecamatan":"320519","desa":"SUKAHATI","kode_desa":"3205192006"},{"nama":"TPS 017","id":35337017,"kode":"3205192006017","tingkat":5,"provinsi":"JAWA BARAT","kode_provinsi":"32","kab_kota":"GARUT","kode_kab_kota":"3205","kecamatan":"CILAWU","kode_kecamatan":"320519","desa":"SUKAHATI","kode_desa":"3205192006"},{"nama":"TPS 018","id":35337018,"kode":"3205192006018","tingkat":5,"provinsi":"JAWA BARAT","kode_provinsi":"32","kab_kota":"GARUT","kode_kab_kota":"3205","kecamatan":"CILAWU","kode_kecamatan":"320519","desa":"SUKAHATI","kode_desa":"3205192006"}]