[{"nama":"TPS 001","id":36947001,"kode":"3209382003001","tingkat":5,"provinsi":"JAWA BARAT","kode_provinsi":"32","kab_kota":"CIREBON","kode_kab_kota":"3209","kecamatan":"GREGED","kode_kecamatan":"320938","desa":"GUMULUNG TONGGOH","kode_desa":"3209382003"},{"nama":"TPS 002","id":36947002,"kode":"3209382003002","tingkat":5,"provinsi":"JAWA BARAT","kode_provinsi":"32","kab_kota":"CIREBON","kode_kab_kota":"3209","kecamatan":"GREGED","kode_kecamatan":"320938","desa":"GUMULUNG TONGGOH","kode_desa":"3209382003"},{"nama":"TPS 003","id":36947003,"kode":"3209382003003","tingkat":5,"provinsi":"JAWA BARAT","kode_provinsi":"32","kab_kota":"CIREBON","kode_kab_kota":"3209","kecamatan":"GREGED","kode_kecamatan":"320938","desa":"GUMULUNG TONGGOH","kode_desa":"3209382003"},{"nama":"TPS 004","id":36947004,"kode":"3209382003004","tingkat":5,"provinsi":"JAWA BARAT","kode_provinsi":"32","kab_kota":"CIREBON","kode_kab_kota":"3209","kecamatan":"GREGED","kode_kecamatan":"320938","desa":"GUMULUNG TONGGOH","kode_desa":"3209382003"},{"nama":"TPS 005","id":36947005,"kode":"3209382003005","tingkat":5,"provinsi":"JAWA BARAT","kode_provinsi":"32","kab_kota":"CIREBON","kode_kab_kota":"3209","kecamatan":"GREGED","kode_kecamatan":"320938","desa":"GUMULUNG TONGGOH","kode_desa":"3209382003"},{"nama":"TPS 006","id":36947006,"kode":"3209382003006","tingkat":5,"provinsi":"JAWA BARAT","kode_provinsi":"32","kab_kota":"CIREBON","kode_kab_kota":"3209","kecamatan":"GREGED","kode_kecamatan":"320938","desa":"GUMULUNG TONGGOH","kode_desa":"3209382003"},{"nama":"TPS 007","id":36947007,"kode":"3209382003007","tingkat":5,"provinsi":"JAWA BARAT","kode_provinsi":"32","kab_kota":"CIREBON","kode_kab_kota":"3209","kecamatan":"GREGED","kode_kecamatan":"320938","desa":"GUMULUNG TONGGOH","kode_desa":"3209382003"},{"nama":"TPS 008","id":36947008,"kode":"3209382003008","tingkat":5,"provinsi":"JAWA BARAT","kode_provinsi":"32","kab_kota":"CIREBON","kode_kab_kota":"3209","kecamatan":"GREGED","kode_kecamatan":"320938","desa":"GUMULUNG TONGGOH","kode_desa":"3209382003"},{"nama":"TPS 009","id":36947009,"kode":"3209382003009","tingkat":5,"provinsi":"JAWA BARAT","kode_provinsi":"32","kab_kota":"CIREBON","kode_kab_kota":"3209","kecamatan":"GREGED","kode_kecamatan":"320938","desa":"GUMULUNG TONGGOH","kode_desa":"3209382003"},{"nama":"TPS 010","id":36947010,"kode":"3209382003010","tingkat":5,"provinsi":"JAWA BARAT","kode_provinsi":"32","kab_kota":"CIREBON","kode_kab_kota":"3209","kecamatan":"GREGED","kode_kecamatan":"320938","desa":"GUMULUNG TONGGOH","kode_desa":"3209382003"},{"nama":"TPS 011","id":36947011,"kode":"3209382003011","tingkat":5,"provinsi":"JAWA BARAT","kode_provinsi":"32","kab_kota":"CIREBON","kode_kab_kota":"3209","kecamatan":"GREGED","kode_kecamatan":"320938","desa":"GUMULUNG TONGGOH","kode_desa":"3209382003"},{"nama":"TPS 012","id":36947012,"kode":"3209382003012","tingkat":5,"provinsi":"JAWA BARAT","kode_provinsi":"32","kab_kota":"CIREBON","kode_kab_kota":"3209","kecamatan":"GREGED","kode_kecamatan":"320938","desa":"GUMULUNG TONGGOH","kode_desa":"3209382003"},{"nama":"TPS 013","id":36947013,"kode":"3209382003013","tingkat":5,"provinsi":"JAWA BARAT","kode_provinsi":"32","kab_kota":"CIREBON","kode_kab_kota":"3209","kecamatan":"GREGED","kode_kecamatan":"320938","desa":"GUMULUNG TONGGOH","kode_desa":"3209382003"},{"nama":"TPS 014","id":36947014,"kode":"3209382003014","tingkat":5,"provinsi":"JAWA BARAT","kode_provinsi":"32","kab_kota":"CIREBON","kode_kab_kota":"3209","kecamatan":"GREGED","kode_kecamatan":"320938","desa":"GUMULUNG TONGGOH","kode_desa":"3209382003"},{"nama":"TPS 015","id":36947015,"kode":"3209382003015","tingkat":5,"provinsi":"JAWA BARAT","kode_provinsi":"32","kab_kota":"CIREBON","kode_kab_kota":"3209","kecamatan":"GREGED","kode_kecamatan":"320938","desa":"GUMULUNG TONGGOH","kode_desa":"3209382003"},{"nama":"TPS 016","id":36947016,"kode":"3209382003016","tingkat":5,"provinsi":"JAWA BARAT","kode_provinsi":"32","kab_kota":"CIREBON","kode_kab_kota":"3209","kecamatan":"GREGED","kode_kecamatan":"320938","desa":"GUMULUNG TONGGOH","kode_desa":"3209382003"},{"nama":"TPS 017","id":36947017,"kode":"3209382003017","tingkat":5,"provinsi":"JAWA BARAT","kode_provinsi":"32","kab_kota":"CIREBON","kode_kab_kota":"3209","kecamatan":"GREGED","kode_kecamatan":"320938","desa":"GUMULUNG TONGGOH","kode_desa":"3209382003"},{"nama":"TPS 018","id":36947018,"kode":"3209382003018","tingkat":5,"provinsi":"JAWA BARAT","kode_provinsi":"32","kab_kota":"CIREBON","kode_kab_kota":"3209","kecamatan":"GREGED","kode_kecamatan":"320938","desa":"GUMULUNG TONGGOH","kode_desa":"3209382003"},{"nama":"TPS 019","id":36947019,"kode":"3209382003019","tingkat":5,"provinsi":"JAWA BARAT","kode_provinsi":"32","kab_kota":"CIREBON","kode_kab_kota":"3209","kecamatan":"GREGED","kode_kecamatan":"320938","desa":"GUMULUNG TONGGOH","kode_desa":"3209382003"},{"nama":"TPS 020","id":36947020,"kode":"3209382003020","tingkat":5,"provinsi":"JAWA BARAT","kode_provinsi":"32","kab_kota":"CIREBON","kode_kab_kota":"3209","kecamatan":"GREGED","kode_kecamatan":"320938","desa":"GUMULUNG TONGGOH","kode_desa":"3209382003"},{"nama":"TPS 021","id":36947021,"kode":"3209382003021","tingkat":5,"provinsi":"JAWA BARAT","kode_provinsi":"32","kab_kota":"CIREBON","kode_kab_kota":"3209","kecamatan":"GREGED","kode_kecamatan":"320938","desa":"GUMULUNG TONGGOH","kode_desa":"3209382003"},{"nama":"TPS 022","id":36947022,"kode":"3209382003022","tingkat":5,"provinsi":"JAWA BARAT","kode_provinsi":"32","kab_kota":"CIREBON","kode_kab_kota":"3209","kecamatan":"GREGED","kode_kecamatan":"320938","desa":"GUMULUNG TONGGOH","kode_desa":"3209382003"},{"nama":"TPS 023","id":36947023,"kode":"3209382003023","tingkat":5,"provinsi":"JAWA BARAT","kode_provinsi":"32","kab_kota":"CIREBON","kode_kab_kota":"3209","kecamatan":"GREGED","kode_kecamatan":"320938","desa":"GUMULUNG TONGGOH","kode_desa":"3209382003"},{"nama":"TPS 024","id":36947024,"kode":"3209382003024","tingkat":5,"provinsi":"JAWA BARAT","kode_provinsi":"32","kab_kota":"CIREBON","kode_kab_kota":"3209","kecamatan":"GREGED","kode_kecamatan":"320938","desa":"GUMULUNG TONGGOH","kode_desa":"3209382003"},{"nama":"TPS 025","id":36947025,"kode":"3209382003025","tingkat":5,"provinsi":"JAWA BARAT","kode_provinsi":"32","kab_kota":"CIREBON","kode_kab_kota":"3209","kecamatan":"GREGED","kode_kecamatan":"320938","desa":"GUMULUNG TONGGOH","kode_desa":"3209382003"},{"nama":"TPS 026","id":36947026,"kode":"3209382003026","tingkat":5,"provinsi":"JAWA BARAT","kode_provinsi":"32","kab_kota":"CIREBON","kode_kab_kota":"3209","kecamatan":"GREGED","kode_kecamatan":"320938","desa":"GUMULUNG TONGGOH","kode_desa":"3209382003"},{"nama":"TPS 027","id":36947027,"kode":"3209382003027","tingkat":5,"provinsi":"JAWA BARAT","kode_provinsi":"32","kab_kota":"CIREBON","kode_kab_kota":"3209","kecamatan":"GREGED","kode_kecamatan":"320938","desa":"GUMULUNG TONGGOH","kode_desa":"3209382003"}]