[{"nama":"TPS 001","id":37796001,"kode":"3212192007001","tingkat":5,"provinsi":"JAWA BARAT","kode_provinsi":"32","kab_kota":"INDRAMAYU","kode_kab_kota":"3212","kecamatan":"ARAHAN","kode_kecamatan":"321219","desa":"SUKASARI","kode_desa":"3212192007"},{"nama":"TPS 002","id":37796002,"kode":"3212192007002","tingkat":5,"provinsi":"JAWA BARAT","kode_provinsi":"32","kab_kota":"INDRAMAYU","kode_kab_kota":"3212","kecamatan":"ARAHAN","kode_kecamatan":"321219","desa":"SUKASARI","kode_desa":"3212192007"},{"nama":"TPS 003","id":37796003,"kode":"3212192007003","tingkat":5,"provinsi":"JAWA BARAT","kode_provinsi":"32","kab_kota":"INDRAMAYU","kode_kab_kota":"3212","kecamatan":"ARAHAN","kode_kecamatan":"321219","desa":"SUKASARI","kode_desa":"3212192007"},{"nama":"TPS 004","id":37796004,"kode":"3212192007004","tingkat":5,"provinsi":"JAWA BARAT","kode_provinsi":"32","kab_kota":"INDRAMAYU","kode_kab_kota":"3212","kecamatan":"ARAHAN","kode_kecamatan":"321219","desa":"SUKASARI","kode_desa":"3212192007"},{"nama":"TPS 005","id":37796005,"kode":"3212192007005","tingkat":5,"provinsi":"JAWA BARAT","kode_provinsi":"32","kab_kota":"INDRAMAYU","kode_kab_kota":"3212","kecamatan":"ARAHAN","kode_kecamatan":"321219","desa":"SUKASARI","kode_desa":"3212192007"},{"nama":"TPS 006","id":37796006,"kode":"3212192007006","tingkat":5,"provinsi":"JAWA BARAT","kode_provinsi":"32","kab_kota":"INDRAMAYU","kode_kab_kota":"3212","kecamatan":"ARAHAN","kode_kecamatan":"321219","desa":"SUKASARI","kode_desa":"3212192007"},{"nama":"TPS 007","id":37796007,"kode":"3212192007007","tingkat":5,"provinsi":"JAWA BARAT","kode_provinsi":"32","kab_kota":"INDRAMAYU","kode_kab_kota":"3212","kecamatan":"ARAHAN","kode_kecamatan":"321219","desa":"SUKASARI","kode_desa":"3212192007"},{"nama":"TPS 008","id":37796008,"kode":"3212192007008","tingkat":5,"provinsi":"JAWA BARAT","kode_provinsi":"32","kab_kota":"INDRAMAYU","kode_kab_kota":"3212","kecamatan":"ARAHAN","kode_kecamatan":"321219","desa":"SUKASARI","kode_desa":"3212192007"},{"nama":"TPS 009","id":37796009,"kode":"3212192007009","tingkat":5,"provinsi":"JAWA BARAT","kode_provinsi":"32","kab_kota":"INDRAMAYU","kode_kab_kota":"3212","kecamatan":"ARAHAN","kode_kecamatan":"321219","desa":"SUKASARI","kode_desa":"3212192007"},{"nama":"TPS 010","id":37796010,"kode":"3212192007010","tingkat":5,"provinsi":"JAWA BARAT","kode_provinsi":"32","kab_kota":"INDRAMAYU","kode_kab_kota":"3212","kecamatan":"ARAHAN","kode_kecamatan":"321219","desa":"SUKASARI","kode_desa":"3212192007"},{"nama":"TPS 011","id":37796011,"kode":"3212192007011","tingkat":5,"provinsi":"JAWA BARAT","kode_provinsi":"32","kab_kota":"INDRAMAYU","kode_kab_kota":"3212","kecamatan":"ARAHAN","kode_kecamatan":"321219","desa":"SUKASARI","kode_desa":"3212192007"},{"nama":"TPS 012","id":37796012,"kode":"3212192007012","tingkat":5,"provinsi":"JAWA BARAT","kode_provinsi":"32","kab_kota":"INDRAMAYU","kode_kab_kota":"3212","kecamatan":"ARAHAN","kode_kecamatan":"321219","desa":"SUKASARI","kode_desa":"3212192007"},{"nama":"TPS 013","id":37796013,"kode":"3212192007013","tingkat":5,"provinsi":"JAWA BARAT","kode_provinsi":"32","kab_kota":"INDRAMAYU","kode_kab_kota":"3212","kecamatan":"ARAHAN","kode_kecamatan":"321219","desa":"SUKASARI","kode_desa":"3212192007"},{"nama":"TPS 014","id":37796014,"kode":"3212192007014","tingkat":5,"provinsi":"JAWA BARAT","kode_provinsi":"32","kab_kota":"INDRAMAYU","kode_kab_kota":"3212","kecamatan":"ARAHAN","kode_kecamatan":"321219","desa":"SUKASARI","kode_desa":"3212192007"},{"nama":"TPS 015","id":37796015,"kode":"3212192007015","tingkat":5,"provinsi":"JAWA BARAT","kode_provinsi":"32","kab_kota":"INDRAMAYU","kode_kab_kota":"3212","kecamatan":"ARAHAN","kode_kecamatan":"321219","desa":"SUKASARI","kode_desa":"3212192007"}]