[{"nama":"TPS 001","id":38728001,"kode":"3216082010001","tingkat":5,"provinsi":"JAWA BARAT","kode_provinsi":"32","kab_kota":"BEKASI","kode_kab_kota":"3216","kecamatan":"CIKARANG BARAT","kode_kecamatan":"321608","desa":"TELAJUNG","kode_desa":"3216082010"},{"nama":"TPS 002","id":38728002,"kode":"3216082010002","tingkat":5,"provinsi":"JAWA BARAT","kode_provinsi":"32","kab_kota":"BEKASI","kode_kab_kota":"3216","kecamatan":"CIKARANG BARAT","kode_kecamatan":"321608","desa":"TELAJUNG","kode_desa":"3216082010"},{"nama":"TPS 003","id":38728003,"kode":"3216082010003","tingkat":5,"provinsi":"JAWA BARAT","kode_provinsi":"32","kab_kota":"BEKASI","kode_kab_kota":"3216","kecamatan":"CIKARANG BARAT","kode_kecamatan":"321608","desa":"TELAJUNG","kode_desa":"3216082010"},{"nama":"TPS 004","id":38728004,"kode":"3216082010004","tingkat":5,"provinsi":"JAWA BARAT","kode_provinsi":"32","kab_kota":"BEKASI","kode_kab_kota":"3216","kecamatan":"CIKARANG BARAT","kode_kecamatan":"321608","desa":"TELAJUNG","kode_desa":"3216082010"},{"nama":"TPS 005","id":38728005,"kode":"3216082010005","tingkat":5,"provinsi":"JAWA BARAT","kode_provinsi":"32","kab_kota":"BEKASI","kode_kab_kota":"3216","kecamatan":"CIKARANG BARAT","kode_kecamatan":"321608","desa":"TELAJUNG","kode_desa":"3216082010"},{"nama":"TPS 006","id":38728006,"kode":"3216082010006","tingkat":5,"provinsi":"JAWA BARAT","kode_provinsi":"32","kab_kota":"BEKASI","kode_kab_kota":"3216","kecamatan":"CIKARANG BARAT","kode_kecamatan":"321608","desa":"TELAJUNG","kode_desa":"3216082010"},{"nama":"TPS 007","id":38728007,"kode":"3216082010007","tingkat":5,"provinsi":"JAWA BARAT","kode_provinsi":"32","kab_kota":"BEKASI","kode_kab_kota":"3216","kecamatan":"CIKARANG BARAT","kode_kecamatan":"321608","desa":"TELAJUNG","kode_desa":"3216082010"},{"nama":"TPS 008","id":38728008,"kode":"3216082010008","tingkat":5,"provinsi":"JAWA BARAT","kode_provinsi":"32","kab_kota":"BEKASI","kode_kab_kota":"3216","kecamatan":"CIKARANG BARAT","kode_kecamatan":"321608","desa":"TELAJUNG","kode_desa":"3216082010"},{"nama":"TPS 009","id":38728009,"kode":"3216082010009","tingkat":5,"provinsi":"JAWA BARAT","kode_provinsi":"32","kab_kota":"BEKASI","kode_kab_kota":"3216","kecamatan":"CIKARANG BARAT","kode_kecamatan":"321608","desa":"TELAJUNG","kode_desa":"3216082010"},{"nama":"TPS 010","id":38728010,"kode":"3216082010010","tingkat":5,"provinsi":"JAWA BARAT","kode_provinsi":"32","kab_kota":"BEKASI","kode_kab_kota":"3216","kecamatan":"CIKARANG BARAT","kode_kecamatan":"321608","desa":"TELAJUNG","kode_desa":"3216082010"},{"nama":"TPS 011","id":38728011,"kode":"3216082010011","tingkat":5,"provinsi":"JAWA BARAT","kode_provinsi":"32","kab_kota":"BEKASI","kode_kab_kota":"3216","kecamatan":"CIKARANG BARAT","kode_kecamatan":"321608","desa":"TELAJUNG","kode_desa":"3216082010"},{"nama":"TPS 012","id":38728012,"kode":"3216082010012","tingkat":5,"provinsi":"JAWA BARAT","kode_provinsi":"32","kab_kota":"BEKASI","kode_kab_kota":"3216","kecamatan":"CIKARANG BARAT","kode_kecamatan":"321608","desa":"TELAJUNG","kode_desa":"3216082010"},{"nama":"TPS 013","id":38728013,"kode":"3216082010013","tingkat":5,"provinsi":"JAWA BARAT","kode_provinsi":"32","kab_kota":"BEKASI","kode_kab_kota":"3216","kecamatan":"CIKARANG BARAT","kode_kecamatan":"321608","desa":"TELAJUNG","kode_desa":"3216082010"},{"nama":"TPS 014","id":38728014,"kode":"3216082010014","tingkat":5,"provinsi":"JAWA BARAT","kode_provinsi":"32","kab_kota":"BEKASI","kode_kab_kota":"3216","kecamatan":"CIKARANG BARAT","kode_kecamatan":"321608","desa":"TELAJUNG","kode_desa":"3216082010"},{"nama":"TPS 015","id":38728015,"kode":"3216082010015","tingkat":5,"provinsi":"JAWA BARAT","kode_provinsi":"32","kab_kota":"BEKASI","kode_kab_kota":"3216","kecamatan":"CIKARANG BARAT","kode_kecamatan":"321608","desa":"TELAJUNG","kode_desa":"3216082010"},{"nama":"TPS 016","id":38728016,"kode":"3216082010016","tingkat":5,"provinsi":"JAWA BARAT","kode_provinsi":"32","kab_kota":"BEKASI","kode_kab_kota":"3216","kecamatan":"CIKARANG BARAT","kode_kecamatan":"321608","desa":"TELAJUNG","kode_desa":"3216082010"},{"nama":"TPS 017","id":38728017,"kode":"3216082010017","tingkat":5,"provinsi":"JAWA BARAT","kode_provinsi":"32","kab_kota":"BEKASI","kode_kab_kota":"3216","kecamatan":"CIKARANG BARAT","kode_kecamatan":"321608","desa":"TELAJUNG","kode_desa":"3216082010"},{"nama":"TPS 018","id":38728018,"kode":"3216082010018","tingkat":5,"provinsi":"JAWA BARAT","kode_provinsi":"32","kab_kota":"BEKASI","kode_kab_kota":"3216","kecamatan":"CIKARANG BARAT","kode_kecamatan":"321608","desa":"TELAJUNG","kode_desa":"3216082010"},{"nama":"TPS 019","id":38728019,"kode":"3216082010019","tingkat":5,"provinsi":"JAWA BARAT","kode_provinsi":"32","kab_kota":"BEKASI","kode_kab_kota":"3216","kecamatan":"CIKARANG BARAT","kode_kecamatan":"321608","desa":"TELAJUNG","kode_desa":"3216082010"},{"nama":"TPS 020","id":38728020,"kode":"3216082010020","tingkat":5,"provinsi":"JAWA BARAT","kode_provinsi":"32","kab_kota":"BEKASI","kode_kab_kota":"3216","kecamatan":"CIKARANG BARAT","kode_kecamatan":"321608","desa":"TELAJUNG","kode_desa":"3216082010"},{"nama":"TPS 021","id":38728021,"kode":"3216082010021","tingkat":5,"provinsi":"JAWA BARAT","kode_provinsi":"32","kab_kota":"BEKASI","kode_kab_kota":"3216","kecamatan":"CIKARANG BARAT","kode_kecamatan":"321608","desa":"TELAJUNG","kode_desa":"3216082010"},{"nama":"TPS 022","id":38728022,"kode":"3216082010022","tingkat":5,"provinsi":"JAWA BARAT","kode_provinsi":"32","kab_kota":"BEKASI","kode_kab_kota":"3216","kecamatan":"CIKARANG BARAT","kode_kecamatan":"321608","desa":"TELAJUNG","kode_desa":"3216082010"},{"nama":"TPS 023","id":38728023,"kode":"3216082010023","tingkat":5,"provinsi":"JAWA BARAT","kode_provinsi":"32","kab_kota":"BEKASI","kode_kab_kota":"3216","kecamatan":"CIKARANG BARAT","kode_kecamatan":"321608","desa":"TELAJUNG","kode_desa":"3216082010"},{"nama":"TPS 024","id":38728024,"kode":"3216082010024","tingkat":5,"provinsi":"JAWA BARAT","kode_provinsi":"32","kab_kota":"BEKASI","kode_kab_kota":"3216","kecamatan":"CIKARANG BARAT","kode_kecamatan":"321608","desa":"TELAJUNG","kode_desa":"3216082010"},{"nama":"TPS 025","id":38728025,"kode":"3216082010025","tingkat":5,"provinsi":"JAWA BARAT","kode_provinsi":"32","kab_kota":"BEKASI","kode_kab_kota":"3216","kecamatan":"CIKARANG BARAT","kode_kecamatan":"321608","desa":"TELAJUNG","kode_desa":"3216082010"},{"nama":"TPS 026","id":38728026,"kode":"3216082010026","tingkat":5,"provinsi":"JAWA BARAT","kode_provinsi":"32","kab_kota":"BEKASI","kode_kab_kota":"3216","kecamatan":"CIKARANG BARAT","kode_kecamatan":"321608","desa":"TELAJUNG","kode_desa":"3216082010"},{"nama":"TPS 027","id":38728027,"kode":"3216082010027","tingkat":5,"provinsi":"JAWA BARAT","kode_provinsi":"32","kab_kota":"BEKASI","kode_kab_kota":"3216","kecamatan":"CIKARANG BARAT","kode_kecamatan":"321608","desa":"TELAJUNG","kode_desa":"3216082010"},{"nama":"TPS 028","id":38728028,"kode":"3216082010028","tingkat":5,"provinsi":"JAWA BARAT","kode_provinsi":"32","kab_kota":"BEKASI","kode_kab_kota":"3216","kecamatan":"CIKARANG BARAT","kode_kecamatan":"321608","desa":"TELAJUNG","kode_desa":"3216082010"},{"nama":"TPS 029","id":38728029,"kode":"3216082010029","tingkat":5,"provinsi":"JAWA BARAT","kode_provinsi":"32","kab_kota":"BEKASI","kode_kab_kota":"3216","kecamatan":"CIKARANG BARAT","kode_kecamatan":"321608","desa":"TELAJUNG","kode_desa":"3216082010"},{"nama":"TPS 030","id":38728030,"kode":"3216082010030","tingkat":5,"provinsi":"JAWA BARAT","kode_provinsi":"32","kab_kota":"BEKASI","kode_kab_kota":"3216","kecamatan":"CIKARANG BARAT","kode_kecamatan":"321608","desa":"TELAJUNG","kode_desa":"3216082010"},{"nama":"TPS 031","id":38728031,"kode":"3216082010031","tingkat":5,"provinsi":"JAWA BARAT","kode_provinsi":"32","kab_kota":"BEKASI","kode_kab_kota":"3216","kecamatan":"CIKARANG BARAT","kode_kecamatan":"321608","desa":"TELAJUNG","kode_desa":"3216082010"},{"nama":"TPS 032","id":38728032,"kode":"3216082010032","tingkat":5,"provinsi":"JAWA BARAT","kode_provinsi":"32","kab_kota":"BEKASI","kode_kab_kota":"3216","kecamatan":"CIKARANG BARAT","kode_kecamatan":"321608","desa":"TELAJUNG","kode_desa":"3216082010"},{"nama":"TPS 033","id":38728033,"kode":"3216082010033","tingkat":5,"provinsi":"JAWA BARAT","kode_provinsi":"32","kab_kota":"BEKASI","kode_kab_kota":"3216","kecamatan":"CIKARANG BARAT","kode_kecamatan":"321608","desa":"TELAJUNG","kode_desa":"3216082010"},{"nama":"TPS 034","id":38728034,"kode":"3216082010034","tingkat":5,"provinsi":"JAWA BARAT","kode_provinsi":"32","kab_kota":"BEKASI","kode_kab_kota":"3216","kecamatan":"CIKARANG BARAT","kode_kecamatan":"321608","desa":"TELAJUNG","kode_desa":"3216082010"},{"nama":"TPS 035","id":38728035,"kode":"3216082010035","tingkat":5,"provinsi":"JAWA BARAT","kode_provinsi":"32","kab_kota":"BEKASI","kode_kab_kota":"3216","kecamatan":"CIKARANG BARAT","kode_kecamatan":"321608","desa":"TELAJUNG","kode_desa":"3216082010"},{"nama":"TPS 036","id":38728036,"kode":"3216082010036","tingkat":5,"provinsi":"JAWA BARAT","kode_provinsi":"32","kab_kota":"BEKASI","kode_kab_kota":"3216","kecamatan":"CIKARANG BARAT","kode_kecamatan":"321608","desa":"TELAJUNG","kode_desa":"3216082010"},{"nama":"TPS 037","id":38728037,"kode":"3216082010037","tingkat":5,"provinsi":"JAWA BARAT","kode_provinsi":"32","kab_kota":"BEKASI","kode_kab_kota":"3216","kecamatan":"CIKARANG BARAT","kode_kecamatan":"321608","desa":"TELAJUNG","kode_desa":"3216082010"},{"nama":"TPS 038","id":38728038,"kode":"3216082010038","tingkat":5,"provinsi":"JAWA BARAT","kode_provinsi":"32","kab_kota":"BEKASI","kode_kab_kota":"3216","kecamatan":"CIKARANG BARAT","kode_kecamatan":"321608","desa":"TELAJUNG","kode_desa":"3216082010"},{"nama":"TPS 039","id":38728039,"kode":"3216082010039","tingkat":5,"provinsi":"JAWA BARAT","kode_provinsi":"32","kab_kota":"BEKASI","kode_kab_kota":"3216","kecamatan":"CIKARANG BARAT","kode_kecamatan":"321608","desa":"TELAJUNG","kode_desa":"3216082010"},{"nama":"TPS 040","id":38728040,"kode":"3216082010040","tingkat":5,"provinsi":"JAWA BARAT","kode_provinsi":"32","kab_kota":"BEKASI","kode_kab_kota":"3216","kecamatan":"CIKARANG BARAT","kode_kecamatan":"321608","desa":"TELAJUNG","kode_desa":"3216082010"},{"nama":"TPS 041","id":38728041,"kode":"3216082010041","tingkat":5,"provinsi":"JAWA BARAT","kode_provinsi":"32","kab_kota":"BEKASI","kode_kab_kota":"3216","kecamatan":"CIKARANG BARAT","kode_kecamatan":"321608","desa":"TELAJUNG","kode_desa":"3216082010"},{"nama":"TPS 042","id":38728042,"kode":"3216082010042","tingkat":5,"provinsi":"JAWA BARAT","kode_provinsi":"32","kab_kota":"BEKASI","kode_kab_kota":"3216","kecamatan":"CIKARANG BARAT","kode_kecamatan":"321608","desa":"TELAJUNG","kode_desa":"3216082010"},{"nama":"TPS 043","id":38728043,"kode":"3216082010043","tingkat":5,"provinsi":"JAWA BARAT","kode_provinsi":"32","kab_kota":"BEKASI","kode_kab_kota":"3216","kecamatan":"CIKARANG BARAT","kode_kecamatan":"321608","desa":"TELAJUNG","kode_desa":"3216082010"},{"nama":"TPS 044","id":38728044,"kode":"3216082010044","tingkat":5,"provinsi":"JAWA BARAT","kode_provinsi":"32","kab_kota":"BEKASI","kode_kab_kota":"3216","kecamatan":"CIKARANG BARAT","kode_kecamatan":"321608","desa":"TELAJUNG","kode_desa":"3216082010"},{"nama":"TPS 045","id":38728045,"kode":"3216082010045","tingkat":5,"provinsi":"JAWA BARAT","kode_provinsi":"32","kab_kota":"BEKASI","kode_kab_kota":"3216","kecamatan":"CIKARANG BARAT","kode_kecamatan":"321608","desa":"TELAJUNG","kode_desa":"3216082010"},{"nama":"TPS 046","id":38728046,"kode":"3216082010046","tingkat":5,"provinsi":"JAWA BARAT","kode_provinsi":"32","kab_kota":"BEKASI","kode_kab_kota":"3216","kecamatan":"CIKARANG BARAT","kode_kecamatan":"321608","desa":"TELAJUNG","kode_desa":"3216082010"},{"nama":"TPS 047","id":38728047,"kode":"3216082010047","tingkat":5,"provinsi":"JAWA BARAT","kode_provinsi":"32","kab_kota":"BEKASI","kode_kab_kota":"3216","kecamatan":"CIKARANG BARAT","kode_kecamatan":"321608","desa":"TELAJUNG","kode_desa":"3216082010"},{"nama":"TPS 048","id":38728048,"kode":"3216082010048","tingkat":5,"provinsi":"JAWA BARAT","kode_provinsi":"32","kab_kota":"BEKASI","kode_kab_kota":"3216","kecamatan":"CIKARANG BARAT","kode_kecamatan":"321608","desa":"TELAJUNG","kode_desa":"3216082010"},{"nama":"TPS 049","id":38728049,"kode":"3216082010049","tingkat":5,"provinsi":"JAWA BARAT","kode_provinsi":"32","kab_kota":"BEKASI","kode_kab_kota":"3216","kecamatan":"CIKARANG BARAT","kode_kecamatan":"321608","desa":"TELAJUNG","kode_desa":"3216082010"},{"nama":"TPS 050","id":38728050,"kode":"3216082010050","tingkat":5,"provinsi":"JAWA BARAT","kode_provinsi":"32","kab_kota":"BEKASI","kode_kab_kota":"3216","kecamatan":"CIKARANG BARAT","kode_kecamatan":"321608","desa":"TELAJUNG","kode_desa":"3216082010"},{"nama":"TPS 051","id":38728051,"kode":"3216082010051","tingkat":5,"provinsi":"JAWA BARAT","kode_provinsi":"32","kab_kota":"BEKASI","kode_kab_kota":"3216","kecamatan":"CIKARANG BARAT","kode_kecamatan":"321608","desa":"TELAJUNG","kode_desa":"3216082010"},{"nama":"TPS 052","id":38728052,"kode":"3216082010052","tingkat":5,"provinsi":"JAWA BARAT","kode_provinsi":"32","kab_kota":"BEKASI","kode_kab_kota":"3216","kecamatan":"CIKARANG BARAT","kode_kecamatan":"321608","desa":"TELAJUNG","kode_desa":"3216082010"},{"nama":"TPS 053","id":38728053,"kode":"3216082010053","tingkat":5,"provinsi":"JAWA BARAT","kode_provinsi":"32","kab_kota":"BEKASI","kode_kab_kota":"3216","kecamatan":"CIKARANG BARAT","kode_kecamatan":"321608","desa":"TELAJUNG","kode_desa":"3216082010"},{"nama":"TPS 054","id":38728054,"kode":"3216082010054","tingkat":5,"provinsi":"JAWA BARAT","kode_provinsi":"32","kab_kota":"BEKASI","kode_kab_kota":"3216","kecamatan":"CIKARANG BARAT","kode_kecamatan":"321608","desa":"TELAJUNG","kode_desa":"3216082010"},{"nama":"TPS 055","id":38728055,"kode":"3216082010055","tingkat":5,"provinsi":"JAWA BARAT","kode_provinsi":"32","kab_kota":"BEKASI","kode_kab_kota":"3216","kecamatan":"CIKARANG BARAT","kode_kecamatan":"321608","desa":"TELAJUNG","kode_desa":"3216082010"},{"nama":"TPS 056","id":38728056,"kode":"3216082010056","tingkat":5,"provinsi":"JAWA BARAT","kode_provinsi":"32","kab_kota":"BEKASI","kode_kab_kota":"3216","kecamatan":"CIKARANG BARAT","kode_kecamatan":"321608","desa":"TELAJUNG","kode_desa":"3216082010"},{"nama":"TPS 057","id":38728057,"kode":"3216082010057","tingkat":5,"provinsi":"JAWA BARAT","kode_provinsi":"32","kab_kota":"BEKASI","kode_kab_kota":"3216","kecamatan":"CIKARANG BARAT","kode_kecamatan":"321608","desa":"TELAJUNG","kode_desa":"3216082010"},{"nama":"TPS 058","id":38728058,"kode":"3216082010058","tingkat":5,"provinsi":"JAWA BARAT","kode_provinsi":"32","kab_kota":"BEKASI","kode_kab_kota":"3216","kecamatan":"CIKARANG BARAT","kode_kecamatan":"321608","desa":"TELAJUNG","kode_desa":"3216082010"},{"nama":"TPS 059","id":38728059,"kode":"3216082010059","tingkat":5,"provinsi":"JAWA BARAT","kode_provinsi":"32","kab_kota":"BEKASI","kode_kab_kota":"3216","kecamatan":"CIKARANG BARAT","kode_kecamatan":"321608","desa":"TELAJUNG","kode_desa":"3216082010"},{"nama":"TPS 060","id":38728060,"kode":"3216082010060","tingkat":5,"provinsi":"JAWA BARAT","kode_provinsi":"32","kab_kota":"BEKASI","kode_kab_kota":"3216","kecamatan":"CIKARANG BARAT","kode_kecamatan":"321608","desa":"TELAJUNG","kode_desa":"3216082010"},{"nama":"TPS 061","id":38728061,"kode":"3216082010061","tingkat":5,"provinsi":"JAWA BARAT","kode_provinsi":"32","kab_kota":"BEKASI","kode_kab_kota":"3216","kecamatan":"CIKARANG BARAT","kode_kecamatan":"321608","desa":"TELAJUNG","kode_desa":"3216082010"},{"nama":"TPS 062","id":38728062,"kode":"3216082010062","tingkat":5,"provinsi":"JAWA BARAT","kode_provinsi":"32","kab_kota":"BEKASI","kode_kab_kota":"3216","kecamatan":"CIKARANG BARAT","kode_kecamatan":"321608","desa":"TELAJUNG","kode_desa":"3216082010"},{"nama":"TPS 063","id":38728063,"kode":"3216082010063","tingkat":5,"provinsi":"JAWA BARAT","kode_provinsi":"32","kab_kota":"BEKASI","kode_kab_kota":"3216","kecamatan":"CIKARANG BARAT","kode_kecamatan":"321608","desa":"TELAJUNG","kode_desa":"3216082010"},{"nama":"TPS 064","id":38728064,"kode":"3216082010064","tingkat":5,"provinsi":"JAWA BARAT","kode_provinsi":"32","kab_kota":"BEKASI","kode_kab_kota":"3216","kecamatan":"CIKARANG BARAT","kode_kecamatan":"321608","desa":"TELAJUNG","kode_desa":"3216082010"},{"nama":"TPS 065","id":38728065,"kode":"3216082010065","tingkat":5,"provinsi":"JAWA BARAT","kode_provinsi":"32","kab_kota":"BEKASI","kode_kab_kota":"3216","kecamatan":"CIKARANG BARAT","kode_kecamatan":"321608","desa":"TELAJUNG","kode_desa":"3216082010"},{"nama":"TPS 066","id":38728066,"kode":"3216082010066","tingkat":5,"provinsi":"JAWA BARAT","kode_provinsi":"32","kab_kota":"BEKASI","kode_kab_kota":"3216","kecamatan":"CIKARANG BARAT","kode_kecamatan":"321608","desa":"TELAJUNG","kode_desa":"3216082010"},{"nama":"TPS 067","id":38728067,"kode":"3216082010067","tingkat":5,"provinsi":"JAWA BARAT","kode_provinsi":"32","kab_kota":"BEKASI","kode_kab_kota":"3216","kecamatan":"CIKARANG BARAT","kode_kecamatan":"321608","desa":"TELAJUNG","kode_desa":"3216082010"},{"nama":"TPS 068","id":38728068,"kode":"3216082010068","tingkat":5,"provinsi":"JAWA BARAT","kode_provinsi":"32","kab_kota":"BEKASI","kode_kab_kota":"3216","kecamatan":"CIKARANG BARAT","kode_kecamatan":"321608","desa":"TELAJUNG","kode_desa":"3216082010"}]