[{"nama":"TPS 001","id":39336001,"kode":"3273251002001","tingkat":5,"provinsi":"JAWA BARAT","kode_provinsi":"32","kab_kota":"KOTA BANDUNG","kode_kab_kota":"3273","kecamatan":"CIBIRU","kode_kecamatan":"327325","desa":"CIPADUNG","kode_desa":"3273251002"},{"nama":"TPS 002","id":39336002,"kode":"3273251002002","tingkat":5,"provinsi":"JAWA BARAT","kode_provinsi":"32","kab_kota":"KOTA BANDUNG","kode_kab_kota":"3273","kecamatan":"CIBIRU","kode_kecamatan":"327325","desa":"CIPADUNG","kode_desa":"3273251002"},{"nama":"TPS 003","id":39336003,"kode":"3273251002003","tingkat":5,"provinsi":"JAWA BARAT","kode_provinsi":"32","kab_kota":"KOTA BANDUNG","kode_kab_kota":"3273","kecamatan":"CIBIRU","kode_kecamatan":"327325","desa":"CIPADUNG","kode_desa":"3273251002"},{"nama":"TPS 004","id":39336004,"kode":"3273251002004","tingkat":5,"provinsi":"JAWA BARAT","kode_provinsi":"32","kab_kota":"KOTA BANDUNG","kode_kab_kota":"3273","kecamatan":"CIBIRU","kode_kecamatan":"327325","desa":"CIPADUNG","kode_desa":"3273251002"},{"nama":"TPS 005","id":39336005,"kode":"3273251002005","tingkat":5,"provinsi":"JAWA BARAT","kode_provinsi":"32","kab_kota":"KOTA BANDUNG","kode_kab_kota":"3273","kecamatan":"CIBIRU","kode_kecamatan":"327325","desa":"CIPADUNG","kode_desa":"3273251002"},{"nama":"TPS 006","id":39336006,"kode":"3273251002006","tingkat":5,"provinsi":"JAWA BARAT","kode_provinsi":"32","kab_kota":"KOTA BANDUNG","kode_kab_kota":"3273","kecamatan":"CIBIRU","kode_kecamatan":"327325","desa":"CIPADUNG","kode_desa":"3273251002"},{"nama":"TPS 007","id":39336007,"kode":"3273251002007","tingkat":5,"provinsi":"JAWA BARAT","kode_provinsi":"32","kab_kota":"KOTA BANDUNG","kode_kab_kota":"3273","kecamatan":"CIBIRU","kode_kecamatan":"327325","desa":"CIPADUNG","kode_desa":"3273251002"},{"nama":"TPS 008","id":39336008,"kode":"3273251002008","tingkat":5,"provinsi":"JAWA BARAT","kode_provinsi":"32","kab_kota":"KOTA BANDUNG","kode_kab_kota":"3273","kecamatan":"CIBIRU","kode_kecamatan":"327325","desa":"CIPADUNG","kode_desa":"3273251002"},{"nama":"TPS 009","id":39336009,"kode":"3273251002009","tingkat":5,"provinsi":"JAWA BARAT","kode_provinsi":"32","kab_kota":"KOTA BANDUNG","kode_kab_kota":"3273","kecamatan":"CIBIRU","kode_kecamatan":"327325","desa":"CIPADUNG","kode_desa":"3273251002"},{"nama":"TPS 010","id":39336010,"kode":"3273251002010","tingkat":5,"provinsi":"JAWA BARAT","kode_provinsi":"32","kab_kota":"KOTA BANDUNG","kode_kab_kota":"3273","kecamatan":"CIBIRU","kode_kecamatan":"327325","desa":"CIPADUNG","kode_desa":"3273251002"},{"nama":"TPS 011","id":39336011,"kode":"3273251002011","tingkat":5,"provinsi":"JAWA BARAT","kode_provinsi":"32","kab_kota":"KOTA BANDUNG","kode_kab_kota":"3273","kecamatan":"CIBIRU","kode_kecamatan":"327325","desa":"CIPADUNG","kode_desa":"3273251002"},{"nama":"TPS 012","id":39336012,"kode":"3273251002012","tingkat":5,"provinsi":"JAWA BARAT","kode_provinsi":"32","kab_kota":"KOTA BANDUNG","kode_kab_kota":"3273","kecamatan":"CIBIRU","kode_kecamatan":"327325","desa":"CIPADUNG","kode_desa":"3273251002"},{"nama":"TPS 013","id":39336013,"kode":"3273251002013","tingkat":5,"provinsi":"JAWA BARAT","kode_provinsi":"32","kab_kota":"KOTA BANDUNG","kode_kab_kota":"3273","kecamatan":"CIBIRU","kode_kecamatan":"327325","desa":"CIPADUNG","kode_desa":"3273251002"},{"nama":"TPS 014","id":39336014,"kode":"3273251002014","tingkat":5,"provinsi":"JAWA BARAT","kode_provinsi":"32","kab_kota":"KOTA BANDUNG","kode_kab_kota":"3273","kecamatan":"CIBIRU","kode_kecamatan":"327325","desa":"CIPADUNG","kode_desa":"3273251002"},{"nama":"TPS 015","id":39336015,"kode":"3273251002015","tingkat":5,"provinsi":"JAWA BARAT","kode_provinsi":"32","kab_kota":"KOTA BANDUNG","kode_kab_kota":"3273","kecamatan":"CIBIRU","kode_kecamatan":"327325","desa":"CIPADUNG","kode_desa":"3273251002"},{"nama":"TPS 016","id":39336016,"kode":"3273251002016","tingkat":5,"provinsi":"JAWA BARAT","kode_provinsi":"32","kab_kota":"KOTA BANDUNG","kode_kab_kota":"3273","kecamatan":"CIBIRU","kode_kecamatan":"327325","desa":"CIPADUNG","kode_desa":"3273251002"},{"nama":"TPS 017","id":39336017,"kode":"3273251002017","tingkat":5,"provinsi":"JAWA BARAT","kode_provinsi":"32","kab_kota":"KOTA BANDUNG","kode_kab_kota":"3273","kecamatan":"CIBIRU","kode_kecamatan":"327325","desa":"CIPADUNG","kode_desa":"3273251002"},{"nama":"TPS 018","id":39336018,"kode":"3273251002018","tingkat":5,"provinsi":"JAWA BARAT","kode_provinsi":"32","kab_kota":"KOTA BANDUNG","kode_kab_kota":"3273","kecamatan":"CIBIRU","kode_kecamatan":"327325","desa":"CIPADUNG","kode_desa":"3273251002"},{"nama":"TPS 019","id":39336019,"kode":"3273251002019","tingkat":5,"provinsi":"JAWA BARAT","kode_provinsi":"32","kab_kota":"KOTA BANDUNG","kode_kab_kota":"3273","kecamatan":"CIBIRU","kode_kecamatan":"327325","desa":"CIPADUNG","kode_desa":"3273251002"},{"nama":"TPS 020","id":39336020,"kode":"3273251002020","tingkat":5,"provinsi":"JAWA BARAT","kode_provinsi":"32","kab_kota":"KOTA BANDUNG","kode_kab_kota":"3273","kecamatan":"CIBIRU","kode_kecamatan":"327325","desa":"CIPADUNG","kode_desa":"3273251002"},{"nama":"TPS 021","id":39336021,"kode":"3273251002021","tingkat":5,"provinsi":"JAWA BARAT","kode_provinsi":"32","kab_kota":"KOTA BANDUNG","kode_kab_kota":"3273","kecamatan":"CIBIRU","kode_kecamatan":"327325","desa":"CIPADUNG","kode_desa":"3273251002"},{"nama":"TPS 022","id":39336022,"kode":"3273251002022","tingkat":5,"provinsi":"JAWA BARAT","kode_provinsi":"32","kab_kota":"KOTA BANDUNG","kode_kab_kota":"3273","kecamatan":"CIBIRU","kode_kecamatan":"327325","desa":"CIPADUNG","kode_desa":"3273251002"},{"nama":"TPS 023","id":39336023,"kode":"3273251002023","tingkat":5,"provinsi":"JAWA BARAT","kode_provinsi":"32","kab_kota":"KOTA BANDUNG","kode_kab_kota":"3273","kecamatan":"CIBIRU","kode_kecamatan":"327325","desa":"CIPADUNG","kode_desa":"3273251002"},{"nama":"TPS 024","id":39336024,"kode":"3273251002024","tingkat":5,"provinsi":"JAWA BARAT","kode_provinsi":"32","kab_kota":"KOTA BANDUNG","kode_kab_kota":"3273","kecamatan":"CIBIRU","kode_kecamatan":"327325","desa":"CIPADUNG","kode_desa":"3273251002"},{"nama":"TPS 025","id":39336025,"kode":"3273251002025","tingkat":5,"provinsi":"JAWA BARAT","kode_provinsi":"32","kab_kota":"KOTA BANDUNG","kode_kab_kota":"3273","kecamatan":"CIBIRU","kode_kecamatan":"327325","desa":"CIPADUNG","kode_desa":"3273251002"},{"nama":"TPS 026","id":39336026,"kode":"3273251002026","tingkat":5,"provinsi":"JAWA BARAT","kode_provinsi":"32","kab_kota":"KOTA BANDUNG","kode_kab_kota":"3273","kecamatan":"CIBIRU","kode_kecamatan":"327325","desa":"CIPADUNG","kode_desa":"3273251002"},{"nama":"TPS 027","id":39336027,"kode":"3273251002027","tingkat":5,"provinsi":"JAWA BARAT","kode_provinsi":"32","kab_kota":"KOTA BANDUNG","kode_kab_kota":"3273","kecamatan":"CIBIRU","kode_kecamatan":"327325","desa":"CIPADUNG","kode_desa":"3273251002"},{"nama":"TPS 028","id":39336028,"kode":"3273251002028","tingkat":5,"provinsi":"JAWA BARAT","kode_provinsi":"32","kab_kota":"KOTA BANDUNG","kode_kab_kota":"3273","kecamatan":"CIBIRU","kode_kecamatan":"327325","desa":"CIPADUNG","kode_desa":"3273251002"},{"nama":"TPS 029","id":39336029,"kode":"3273251002029","tingkat":5,"provinsi":"JAWA BARAT","kode_provinsi":"32","kab_kota":"KOTA BANDUNG","kode_kab_kota":"3273","kecamatan":"CIBIRU","kode_kecamatan":"327325","desa":"CIPADUNG","kode_desa":"3273251002"},{"nama":"TPS 030","id":39336030,"kode":"3273251002030","tingkat":5,"provinsi":"JAWA BARAT","kode_provinsi":"32","kab_kota":"KOTA BANDUNG","kode_kab_kota":"3273","kecamatan":"CIBIRU","kode_kecamatan":"327325","desa":"CIPADUNG","kode_desa":"3273251002"},{"nama":"TPS 031","id":39336031,"kode":"3273251002031","tingkat":5,"provinsi":"JAWA BARAT","kode_provinsi":"32","kab_kota":"KOTA BANDUNG","kode_kab_kota":"3273","kecamatan":"CIBIRU","kode_kecamatan":"327325","desa":"CIPADUNG","kode_desa":"3273251002"},{"nama":"TPS 032","id":39336032,"kode":"3273251002032","tingkat":5,"provinsi":"JAWA BARAT","kode_provinsi":"32","kab_kota":"KOTA BANDUNG","kode_kab_kota":"3273","kecamatan":"CIBIRU","kode_kecamatan":"327325","desa":"CIPADUNG","kode_desa":"3273251002"},{"nama":"TPS 033","id":39336033,"kode":"3273251002033","tingkat":5,"provinsi":"JAWA BARAT","kode_provinsi":"32","kab_kota":"KOTA BANDUNG","kode_kab_kota":"3273","kecamatan":"CIBIRU","kode_kecamatan":"327325","desa":"CIPADUNG","kode_desa":"3273251002"},{"nama":"TPS 034","id":39336034,"kode":"3273251002034","tingkat":5,"provinsi":"JAWA BARAT","kode_provinsi":"32","kab_kota":"KOTA BANDUNG","kode_kab_kota":"3273","kecamatan":"CIBIRU","kode_kecamatan":"327325","desa":"CIPADUNG","kode_desa":"3273251002"},{"nama":"TPS 035","id":39336035,"kode":"3273251002035","tingkat":5,"provinsi":"JAWA BARAT","kode_provinsi":"32","kab_kota":"KOTA BANDUNG","kode_kab_kota":"3273","kecamatan":"CIBIRU","kode_kecamatan":"327325","desa":"CIPADUNG","kode_desa":"3273251002"},{"nama":"TPS 036","id":39336036,"kode":"3273251002036","tingkat":5,"provinsi":"JAWA BARAT","kode_provinsi":"32","kab_kota":"KOTA BANDUNG","kode_kab_kota":"3273","kecamatan":"CIBIRU","kode_kecamatan":"327325","desa":"CIPADUNG","kode_desa":"3273251002"},{"nama":"TPS 037","id":39336037,"kode":"3273251002037","tingkat":5,"provinsi":"JAWA BARAT","kode_provinsi":"32","kab_kota":"KOTA BANDUNG","kode_kab_kota":"3273","kecamatan":"CIBIRU","kode_kecamatan":"327325","desa":"CIPADUNG","kode_desa":"3273251002"},{"nama":"TPS 038","id":39336038,"kode":"3273251002038","tingkat":5,"provinsi":"JAWA BARAT","kode_provinsi":"32","kab_kota":"KOTA BANDUNG","kode_kab_kota":"3273","kecamatan":"CIBIRU","kode_kecamatan":"327325","desa":"CIPADUNG","kode_desa":"3273251002"},{"nama":"TPS 039","id":39336039,"kode":"3273251002039","tingkat":5,"provinsi":"JAWA BARAT","kode_provinsi":"32","kab_kota":"KOTA BANDUNG","kode_kab_kota":"3273","kecamatan":"CIBIRU","kode_kecamatan":"327325","desa":"CIPADUNG","kode_desa":"3273251002"},{"nama":"TPS 040","id":39336040,"kode":"3273251002040","tingkat":5,"provinsi":"JAWA BARAT","kode_provinsi":"32","kab_kota":"KOTA BANDUNG","kode_kab_kota":"3273","kecamatan":"CIBIRU","kode_kecamatan":"327325","desa":"CIPADUNG","kode_desa":"3273251002"},{"nama":"TPS 041","id":39336041,"kode":"3273251002041","tingkat":5,"provinsi":"JAWA BARAT","kode_provinsi":"32","kab_kota":"KOTA BANDUNG","kode_kab_kota":"3273","kecamatan":"CIBIRU","kode_kecamatan":"327325","desa":"CIPADUNG","kode_desa":"3273251002"},{"nama":"TPS 042","id":39336042,"kode":"3273251002042","tingkat":5,"provinsi":"JAWA BARAT","kode_provinsi":"32","kab_kota":"KOTA BANDUNG","kode_kab_kota":"3273","kecamatan":"CIBIRU","kode_kecamatan":"327325","desa":"CIPADUNG","kode_desa":"3273251002"},{"nama":"TPS 043","id":39336043,"kode":"3273251002043","tingkat":5,"provinsi":"JAWA BARAT","kode_provinsi":"32","kab_kota":"KOTA BANDUNG","kode_kab_kota":"3273","kecamatan":"CIBIRU","kode_kecamatan":"327325","desa":"CIPADUNG","kode_desa":"3273251002"},{"nama":"TPS 044","id":39336044,"kode":"3273251002044","tingkat":5,"provinsi":"JAWA BARAT","kode_provinsi":"32","kab_kota":"KOTA BANDUNG","kode_kab_kota":"3273","kecamatan":"CIBIRU","kode_kecamatan":"327325","desa":"CIPADUNG","kode_desa":"3273251002"},{"nama":"TPS 045","id":39336045,"kode":"3273251002045","tingkat":5,"provinsi":"JAWA BARAT","kode_provinsi":"32","kab_kota":"KOTA BANDUNG","kode_kab_kota":"3273","kecamatan":"CIBIRU","kode_kecamatan":"327325","desa":"CIPADUNG","kode_desa":"3273251002"},{"nama":"TPS 046","id":39336046,"kode":"3273251002046","tingkat":5,"provinsi":"JAWA BARAT","kode_provinsi":"32","kab_kota":"KOTA BANDUNG","kode_kab_kota":"3273","kecamatan":"CIBIRU","kode_kecamatan":"327325","desa":"CIPADUNG","kode_desa":"3273251002"},{"nama":"TPS 047","id":39336047,"kode":"3273251002047","tingkat":5,"provinsi":"JAWA BARAT","kode_provinsi":"32","kab_kota":"KOTA BANDUNG","kode_kab_kota":"3273","kecamatan":"CIBIRU","kode_kecamatan":"327325","desa":"CIPADUNG","kode_desa":"3273251002"},{"nama":"TPS 048","id":39336048,"kode":"3273251002048","tingkat":5,"provinsi":"JAWA BARAT","kode_provinsi":"32","kab_kota":"KOTA BANDUNG","kode_kab_kota":"3273","kecamatan":"CIBIRU","kode_kecamatan":"327325","desa":"CIPADUNG","kode_desa":"3273251002"},{"nama":"TPS 049","id":39336049,"kode":"3273251002049","tingkat":5,"provinsi":"JAWA BARAT","kode_provinsi":"32","kab_kota":"KOTA BANDUNG","kode_kab_kota":"3273","kecamatan":"CIBIRU","kode_kecamatan":"327325","desa":"CIPADUNG","kode_desa":"3273251002"},{"nama":"TPS 050","id":39336050,"kode":"3273251002050","tingkat":5,"provinsi":"JAWA BARAT","kode_provinsi":"32","kab_kota":"KOTA BANDUNG","kode_kab_kota":"3273","kecamatan":"CIBIRU","kode_kecamatan":"327325","desa":"CIPADUNG","kode_desa":"3273251002"},{"nama":"TPS 051","id":39336051,"kode":"3273251002051","tingkat":5,"provinsi":"JAWA BARAT","kode_provinsi":"32","kab_kota":"KOTA BANDUNG","kode_kab_kota":"3273","kecamatan":"CIBIRU","kode_kecamatan":"327325","desa":"CIPADUNG","kode_desa":"3273251002"},{"nama":"TPS 052","id":39336052,"kode":"3273251002052","tingkat":5,"provinsi":"JAWA BARAT","kode_provinsi":"32","kab_kota":"KOTA BANDUNG","kode_kab_kota":"3273","kecamatan":"CIBIRU","kode_kecamatan":"327325","desa":"CIPADUNG","kode_desa":"3273251002"},{"nama":"TPS 053","id":39336053,"kode":"3273251002053","tingkat":5,"provinsi":"JAWA BARAT","kode_provinsi":"32","kab_kota":"KOTA BANDUNG","kode_kab_kota":"3273","kecamatan":"CIBIRU","kode_kecamatan":"327325","desa":"CIPADUNG","kode_desa":"3273251002"},{"nama":"TPS 054","id":39336054,"kode":"3273251002054","tingkat":5,"provinsi":"JAWA BARAT","kode_provinsi":"32","kab_kota":"KOTA BANDUNG","kode_kab_kota":"3273","kecamatan":"CIBIRU","kode_kecamatan":"327325","desa":"CIPADUNG","kode_desa":"3273251002"},{"nama":"TPS 055","id":39336055,"kode":"3273251002055","tingkat":5,"provinsi":"JAWA BARAT","kode_provinsi":"32","kab_kota":"KOTA BANDUNG","kode_kab_kota":"3273","kecamatan":"CIBIRU","kode_kecamatan":"327325","desa":"CIPADUNG","kode_desa":"3273251002"},{"nama":"TPS 056","id":39336056,"kode":"3273251002056","tingkat":5,"provinsi":"JAWA BARAT","kode_provinsi":"32","kab_kota":"KOTA BANDUNG","kode_kab_kota":"3273","kecamatan":"CIBIRU","kode_kecamatan":"327325","desa":"CIPADUNG","kode_desa":"3273251002"},{"nama":"TPS 057","id":39336057,"kode":"3273251002057","tingkat":5,"provinsi":"JAWA BARAT","kode_provinsi":"32","kab_kota":"KOTA BANDUNG","kode_kab_kota":"3273","kecamatan":"CIBIRU","kode_kecamatan":"327325","desa":"CIPADUNG","kode_desa":"3273251002"},{"nama":"TPS 058","id":39336058,"kode":"3273251002058","tingkat":5,"provinsi":"JAWA BARAT","kode_provinsi":"32","kab_kota":"KOTA BANDUNG","kode_kab_kota":"3273","kecamatan":"CIBIRU","kode_kecamatan":"327325","desa":"CIPADUNG","kode_desa":"3273251002"},{"nama":"TPS 059","id":39336059,"kode":"3273251002059","tingkat":5,"provinsi":"JAWA BARAT","kode_provinsi":"32","kab_kota":"KOTA BANDUNG","kode_kab_kota":"3273","kecamatan":"CIBIRU","kode_kecamatan":"327325","desa":"CIPADUNG","kode_desa":"3273251002"},{"nama":"TPS 060","id":39336060,"kode":"3273251002060","tingkat":5,"provinsi":"JAWA BARAT","kode_provinsi":"32","kab_kota":"KOTA BANDUNG","kode_kab_kota":"3273","kecamatan":"CIBIRU","kode_kecamatan":"327325","desa":"CIPADUNG","kode_desa":"3273251002"},{"nama":"TPS 061","id":39336061,"kode":"3273251002061","tingkat":5,"provinsi":"JAWA BARAT","kode_provinsi":"32","kab_kota":"KOTA BANDUNG","kode_kab_kota":"3273","kecamatan":"CIBIRU","kode_kecamatan":"327325","desa":"CIPADUNG","kode_desa":"3273251002"},{"nama":"TPS 062","id":39336062,"kode":"3273251002062","tingkat":5,"provinsi":"JAWA BARAT","kode_provinsi":"32","kab_kota":"KOTA BANDUNG","kode_kab_kota":"3273","kecamatan":"CIBIRU","kode_kecamatan":"327325","desa":"CIPADUNG","kode_desa":"3273251002"},{"nama":"TPS 063","id":39336063,"kode":"3273251002063","tingkat":5,"provinsi":"JAWA BARAT","kode_provinsi":"32","kab_kota":"KOTA BANDUNG","kode_kab_kota":"3273","kecamatan":"CIBIRU","kode_kecamatan":"327325","desa":"CIPADUNG","kode_desa":"3273251002"},{"nama":"TPS 064","id":39336064,"kode":"3273251002064","tingkat":5,"provinsi":"JAWA BARAT","kode_provinsi":"32","kab_kota":"KOTA BANDUNG","kode_kab_kota":"3273","kecamatan":"CIBIRU","kode_kecamatan":"327325","desa":"CIPADUNG","kode_desa":"3273251002"},{"nama":"TPS 065","id":39336065,"kode":"3273251002065","tingkat":5,"provinsi":"JAWA BARAT","kode_provinsi":"32","kab_kota":"KOTA BANDUNG","kode_kab_kota":"3273","kecamatan":"CIBIRU","kode_kecamatan":"327325","desa":"CIPADUNG","kode_desa":"3273251002"},{"nama":"TPS 066","id":39336066,"kode":"3273251002066","tingkat":5,"provinsi":"JAWA BARAT","kode_provinsi":"32","kab_kota":"KOTA BANDUNG","kode_kab_kota":"3273","kecamatan":"CIBIRU","kode_kecamatan":"327325","desa":"CIPADUNG","kode_desa":"3273251002"},{"nama":"TPS 067","id":39336067,"kode":"3273251002067","tingkat":5,"provinsi":"JAWA BARAT","kode_provinsi":"32","kab_kota":"KOTA BANDUNG","kode_kab_kota":"3273","kecamatan":"CIBIRU","kode_kecamatan":"327325","desa":"CIPADUNG","kode_desa":"3273251002"}]