[{"nama":"TPS 001","id":39588001,"kode":"3279012003001","tingkat":5,"provinsi":"JAWA BARAT","kode_provinsi":"32","kab_kota":"KOTA BANJAR","kode_kab_kota":"3279","kecamatan":"BANJAR","kode_kecamatan":"327901","desa":"BALOKANG","kode_desa":"3279012003"},{"nama":"TPS 002","id":39588002,"kode":"3279012003002","tingkat":5,"provinsi":"JAWA BARAT","kode_provinsi":"32","kab_kota":"KOTA BANJAR","kode_kab_kota":"3279","kecamatan":"BANJAR","kode_kecamatan":"327901","desa":"BALOKANG","kode_desa":"3279012003"},{"nama":"TPS 003","id":39588003,"kode":"3279012003003","tingkat":5,"provinsi":"JAWA BARAT","kode_provinsi":"32","kab_kota":"KOTA BANJAR","kode_kab_kota":"3279","kecamatan":"BANJAR","kode_kecamatan":"327901","desa":"BALOKANG","kode_desa":"3279012003"},{"nama":"TPS 004","id":39588004,"kode":"3279012003004","tingkat":5,"provinsi":"JAWA BARAT","kode_provinsi":"32","kab_kota":"KOTA BANJAR","kode_kab_kota":"3279","kecamatan":"BANJAR","kode_kecamatan":"327901","desa":"BALOKANG","kode_desa":"3279012003"},{"nama":"TPS 005","id":39588005,"kode":"3279012003005","tingkat":5,"provinsi":"JAWA BARAT","kode_provinsi":"32","kab_kota":"KOTA BANJAR","kode_kab_kota":"3279","kecamatan":"BANJAR","kode_kecamatan":"327901","desa":"BALOKANG","kode_desa":"3279012003"},{"nama":"TPS 006","id":39588006,"kode":"3279012003006","tingkat":5,"provinsi":"JAWA BARAT","kode_provinsi":"32","kab_kota":"KOTA BANJAR","kode_kab_kota":"3279","kecamatan":"BANJAR","kode_kecamatan":"327901","desa":"BALOKANG","kode_desa":"3279012003"},{"nama":"TPS 007","id":39588007,"kode":"3279012003007","tingkat":5,"provinsi":"JAWA BARAT","kode_provinsi":"32","kab_kota":"KOTA BANJAR","kode_kab_kota":"3279","kecamatan":"BANJAR","kode_kecamatan":"327901","desa":"BALOKANG","kode_desa":"3279012003"},{"nama":"TPS 008","id":39588008,"kode":"3279012003008","tingkat":5,"provinsi":"JAWA BARAT","kode_provinsi":"32","kab_kota":"KOTA BANJAR","kode_kab_kota":"3279","kecamatan":"BANJAR","kode_kecamatan":"327901","desa":"BALOKANG","kode_desa":"3279012003"},{"nama":"TPS 009","id":39588009,"kode":"3279012003009","tingkat":5,"provinsi":"JAWA BARAT","kode_provinsi":"32","kab_kota":"KOTA BANJAR","kode_kab_kota":"3279","kecamatan":"BANJAR","kode_kecamatan":"327901","desa":"BALOKANG","kode_desa":"3279012003"},{"nama":"TPS 010","id":39588010,"kode":"3279012003010","tingkat":5,"provinsi":"JAWA BARAT","kode_provinsi":"32","kab_kota":"KOTA BANJAR","kode_kab_kota":"3279","kecamatan":"BANJAR","kode_kecamatan":"327901","desa":"BALOKANG","kode_desa":"3279012003"},{"nama":"TPS 011","id":39588011,"kode":"3279012003011","tingkat":5,"provinsi":"JAWA BARAT","kode_provinsi":"32","kab_kota":"KOTA BANJAR","kode_kab_kota":"3279","kecamatan":"BANJAR","kode_kecamatan":"327901","desa":"BALOKANG","kode_desa":"3279012003"},{"nama":"TPS 012","id":39588012,"kode":"3279012003012","tingkat":5,"provinsi":"JAWA BARAT","kode_provinsi":"32","kab_kota":"KOTA BANJAR","kode_kab_kota":"3279","kecamatan":"BANJAR","kode_kecamatan":"327901","desa":"BALOKANG","kode_desa":"3279012003"},{"nama":"TPS 013","id":39588013,"kode":"3279012003013","tingkat":5,"provinsi":"JAWA BARAT","kode_provinsi":"32","kab_kota":"KOTA BANJAR","kode_kab_kota":"3279","kecamatan":"BANJAR","kode_kecamatan":"327901","desa":"BALOKANG","kode_desa":"3279012003"},{"nama":"TPS 014","id":39588014,"kode":"3279012003014","tingkat":5,"provinsi":"JAWA BARAT","kode_provinsi":"32","kab_kota":"KOTA BANJAR","kode_kab_kota":"3279","kecamatan":"BANJAR","kode_kecamatan":"327901","desa":"BALOKANG","kode_desa":"3279012003"},{"nama":"TPS 015","id":39588015,"kode":"3279012003015","tingkat":5,"provinsi":"JAWA BARAT","kode_provinsi":"32","kab_kota":"KOTA BANJAR","kode_kab_kota":"3279","kecamatan":"BANJAR","kode_kecamatan":"327901","desa":"BALOKANG","kode_desa":"3279012003"},{"nama":"TPS 016","id":39588016,"kode":"3279012003016","tingkat":5,"provinsi":"JAWA BARAT","kode_provinsi":"32","kab_kota":"KOTA BANJAR","kode_kab_kota":"3279","kecamatan":"BANJAR","kode_kecamatan":"327901","desa":"BALOKANG","kode_desa":"3279012003"},{"nama":"TPS 017","id":39588017,"kode":"3279012003017","tingkat":5,"provinsi":"JAWA BARAT","kode_provinsi":"32","kab_kota":"KOTA BANJAR","kode_kab_kota":"3279","kecamatan":"BANJAR","kode_kecamatan":"327901","desa":"BALOKANG","kode_desa":"3279012003"},{"nama":"TPS 018","id":39588018,"kode":"3279012003018","tingkat":5,"provinsi":"JAWA BARAT","kode_provinsi":"32","kab_kota":"KOTA BANJAR","kode_kab_kota":"3279","kecamatan":"BANJAR","kode_kecamatan":"327901","desa":"BALOKANG","kode_desa":"3279012003"},{"nama":"TPS 019","id":39588019,"kode":"3279012003019","tingkat":5,"provinsi":"JAWA BARAT","kode_provinsi":"32","kab_kota":"KOTA BANJAR","kode_kab_kota":"3279","kecamatan":"BANJAR","kode_kecamatan":"327901","desa":"BALOKANG","kode_desa":"3279012003"},{"nama":"TPS 020","id":39588020,"kode":"3279012003020","tingkat":5,"provinsi":"JAWA BARAT","kode_provinsi":"32","kab_kota":"KOTA BANJAR","kode_kab_kota":"3279","kecamatan":"BANJAR","kode_kecamatan":"327901","desa":"BALOKANG","kode_desa":"3279012003"},{"nama":"TPS 021","id":39588021,"kode":"3279012003021","tingkat":5,"provinsi":"JAWA BARAT","kode_provinsi":"32","kab_kota":"KOTA BANJAR","kode_kab_kota":"3279","kecamatan":"BANJAR","kode_kecamatan":"327901","desa":"BALOKANG","kode_desa":"3279012003"},{"nama":"TPS 022","id":39588022,"kode":"3279012003022","tingkat":5,"provinsi":"JAWA BARAT","kode_provinsi":"32","kab_kota":"KOTA BANJAR","kode_kab_kota":"3279","kecamatan":"BANJAR","kode_kecamatan":"327901","desa":"BALOKANG","kode_desa":"3279012003"},{"nama":"TPS 023","id":39588023,"kode":"3279012003023","tingkat":5,"provinsi":"JAWA BARAT","kode_provinsi":"32","kab_kota":"KOTA BANJAR","kode_kab_kota":"3279","kecamatan":"BANJAR","kode_kecamatan":"327901","desa":"BALOKANG","kode_desa":"3279012003"},{"nama":"TPS 024","id":39588024,"kode":"3279012003024","tingkat":5,"provinsi":"JAWA BARAT","kode_provinsi":"32","kab_kota":"KOTA BANJAR","kode_kab_kota":"3279","kecamatan":"BANJAR","kode_kecamatan":"327901","desa":"BALOKANG","kode_desa":"3279012003"},{"nama":"TPS 025","id":39588025,"kode":"3279012003025","tingkat":5,"provinsi":"JAWA BARAT","kode_provinsi":"32","kab_kota":"KOTA BANJAR","kode_kab_kota":"3279","kecamatan":"BANJAR","kode_kecamatan":"327901","desa":"BALOKANG","kode_desa":"3279012003"},{"nama":"TPS 026","id":39588026,"kode":"3279012003026","tingkat":5,"provinsi":"JAWA BARAT","kode_provinsi":"32","kab_kota":"KOTA BANJAR","kode_kab_kota":"3279","kecamatan":"BANJAR","kode_kecamatan":"327901","desa":"BALOKANG","kode_desa":"3279012003"},{"nama":"TPS 027","id":39588027,"kode":"3279012003027","tingkat":5,"provinsi":"JAWA BARAT","kode_provinsi":"32","kab_kota":"KOTA BANJAR","kode_kab_kota":"3279","kecamatan":"BANJAR","kode_kecamatan":"327901","desa":"BALOKANG","kode_desa":"3279012003"},{"nama":"TPS 028","id":39588028,"kode":"3279012003028","tingkat":5,"provinsi":"JAWA BARAT","kode_provinsi":"32","kab_kota":"KOTA BANJAR","kode_kab_kota":"3279","kecamatan":"BANJAR","kode_kecamatan":"327901","desa":"BALOKANG","kode_desa":"3279012003"},{"nama":"TPS 029","id":39588029,"kode":"3279012003029","tingkat":5,"provinsi":"JAWA BARAT","kode_provinsi":"32","kab_kota":"KOTA BANJAR","kode_kab_kota":"3279","kecamatan":"BANJAR","kode_kecamatan":"327901","desa":"BALOKANG","kode_desa":"3279012003"},{"nama":"TPS 030","id":39588030,"kode":"3279012003030","tingkat":5,"provinsi":"JAWA BARAT","kode_provinsi":"32","kab_kota":"KOTA BANJAR","kode_kab_kota":"3279","kecamatan":"BANJAR","kode_kecamatan":"327901","desa":"BALOKANG","kode_desa":"3279012003"},{"nama":"TPS 031","id":39588031,"kode":"3279012003031","tingkat":5,"provinsi":"JAWA BARAT","kode_provinsi":"32","kab_kota":"KOTA BANJAR","kode_kab_kota":"3279","kecamatan":"BANJAR","kode_kecamatan":"327901","desa":"BALOKANG","kode_desa":"3279012003"}]